{
"meta":{"test_sets":[],"test_metrics":[],"learn_metrics":[{"best_value":"Min","name":"RMSE"}],"launch_mode":"Train","parameters":"","iteration_count":1000,"learn_sets":["learn"],"name":"experiment"},
"iterations":[
{"learn":[14.61984341],"iteration":0,"passed_time":0.06519680491,"remaining_time":65.13160811},
{"learn":[14.26453264],"iteration":1,"passed_time":0.06622287434,"remaining_time":33.0452143},
{"learn":[13.94182597],"iteration":2,"passed_time":0.06731677588,"remaining_time":22.37160852},
{"learn":[13.59512006],"iteration":3,"passed_time":0.06811868128,"remaining_time":16.96155164},
{"learn":[13.27461944],"iteration":4,"passed_time":0.06893212852,"remaining_time":13.71749358},
{"learn":[13.00325719],"iteration":5,"passed_time":0.06972441004,"remaining_time":11.5510106},
{"learn":[12.70457115],"iteration":6,"passed_time":0.07042702575,"remaining_time":9.990576653},
{"learn":[12.44449968],"iteration":7,"passed_time":0.0712174323,"remaining_time":8.830961605},
{"learn":[12.18855771],"iteration":8,"passed_time":0.07399910352,"remaining_time":8.14812351},
{"learn":[11.90587631],"iteration":9,"passed_time":0.07522187835,"remaining_time":7.446965957},
{"learn":[11.6262434],"iteration":10,"passed_time":0.07622944903,"remaining_time":6.853720463},
{"learn":[11.40998803],"iteration":11,"passed_time":0.07744030802,"remaining_time":6.375918693},
{"learn":[11.16776832],"iteration":12,"passed_time":0.07861179253,"remaining_time":5.968449171},
{"learn":[10.94253634],"iteration":13,"passed_time":0.07959461253,"remaining_time":5.605734854},
{"learn":[10.71354747],"iteration":14,"passed_time":0.08070434786,"remaining_time":5.299585509},
{"learn":[10.47716928],"iteration":15,"passed_time":0.0815406288,"remaining_time":5.014748671},
{"learn":[10.26356045],"iteration":16,"passed_time":0.08258319801,"remaining_time":4.775251979},
{"learn":[10.06643925],"iteration":17,"passed_time":0.08508987287,"remaining_time":4.642125286},
{"learn":[9.864840438],"iteration":18,"passed_time":0.08614090097,"remaining_time":4.447590729},
{"learn":[9.683731722],"iteration":19,"passed_time":0.08723438651,"remaining_time":4.274484939},
{"learn":[9.532151617],"iteration":20,"passed_time":0.08842874572,"remaining_time":4.122463907},
{"learn":[9.363290803],"iteration":21,"passed_time":0.089465982,"remaining_time":3.977169564},
{"learn":[9.205809068],"iteration":22,"passed_time":0.0907445061,"remaining_time":3.854668802},
{"learn":[9.041459267],"iteration":23,"passed_time":0.09195503209,"remaining_time":3.739504638},
{"learn":[8.88133112],"iteration":24,"passed_time":0.09278168816,"remaining_time":3.618485838},
{"learn":[8.747119683],"iteration":25,"passed_time":0.09347876194,"remaining_time":3.501858236},
{"learn":[8.605703866],"iteration":26,"passed_time":0.09421696018,"remaining_time":3.395300084},
{"learn":[8.499336654],"iteration":27,"passed_time":0.09489065927,"remaining_time":3.294061458},
{"learn":[8.36245044],"iteration":28,"passed_time":0.09554327564,"remaining_time":3.199052436},
{"learn":[8.239879788],"iteration":29,"passed_time":0.09619776699,"remaining_time":3.110394466},
{"learn":[8.115349172],"iteration":30,"passed_time":0.0969302153,"remaining_time":3.029850924},
{"learn":[8.001550699],"iteration":31,"passed_time":0.09763824794,"remaining_time":2.953557},
{"learn":[7.888292136],"iteration":32,"passed_time":0.0983299478,"remaining_time":2.88136544},
{"learn":[7.793276229],"iteration":33,"passed_time":0.09898293916,"remaining_time":2.812279977},
{"learn":[7.685698341],"iteration":34,"passed_time":0.09964334743,"remaining_time":2.747309436},
{"learn":[7.582350237],"iteration":35,"passed_time":0.100360088,"remaining_time":2.687420133},
{"learn":[7.480669748],"iteration":36,"passed_time":0.1010252462,"remaining_time":2.629386812},
{"learn":[7.398765022],"iteration":37,"passed_time":0.1018030279,"remaining_time":2.577224021},
{"learn":[7.31453519],"iteration":38,"passed_time":0.1025320602,"remaining_time":2.526495125},
{"learn":[7.232415261],"iteration":39,"passed_time":0.103307342,"remaining_time":2.479376208},
{"learn":[7.157884359],"iteration":40,"passed_time":0.1041489559,"remaining_time":2.43606948},
{"learn":[7.095802149],"iteration":41,"passed_time":0.1049936117,"remaining_time":2.394854286},
{"learn":[7.018760013],"iteration":42,"passed_time":0.1057616435,"remaining_time":2.353811462},
{"learn":[6.942400702],"iteration":43,"passed_time":0.1064973838,"remaining_time":2.313897703},
{"learn":[6.876298651],"iteration":44,"passed_time":0.1071785838,"remaining_time":2.274567723},
{"learn":[6.813423046],"iteration":45,"passed_time":0.1081229883,"remaining_time":2.242376757},
{"learn":[6.751216225],"iteration":46,"passed_time":0.109131267,"remaining_time":2.212810583},
{"learn":[6.690045048],"iteration":47,"passed_time":0.1100283381,"remaining_time":2.182228706},
{"learn":[6.625782965],"iteration":48,"passed_time":0.1109620758,"remaining_time":2.153570083},
{"learn":[6.574706693],"iteration":49,"passed_time":0.1119987701,"remaining_time":2.127976631},
{"learn":[6.526055739],"iteration":50,"passed_time":0.1130525481,"remaining_time":2.103664082},
{"learn":[6.477192022],"iteration":51,"passed_time":0.1140138274,"remaining_time":2.078559777},
{"learn":[6.429037593],"iteration":52,"passed_time":0.1151636042,"remaining_time":2.057734588},
{"learn":[6.37622207],"iteration":53,"passed_time":0.1204838259,"remaining_time":2.110698134},
{"learn":[6.326919493],"iteration":54,"passed_time":0.1215226871,"remaining_time":2.087980715},
{"learn":[6.279276347],"iteration":55,"passed_time":0.1223706759,"remaining_time":2.062819965},
{"learn":[6.233956988],"iteration":56,"passed_time":0.123046251,"remaining_time":2.035659906},
{"learn":[6.192278905],"iteration":57,"passed_time":0.1236970754,"remaining_time":2.009011121},
{"learn":[6.156003497],"iteration":58,"passed_time":0.1244744401,"remaining_time":1.985261833},
{"learn":[6.119618668],"iteration":59,"passed_time":0.1251443472,"remaining_time":1.960594773},
{"learn":[6.085180098],"iteration":60,"passed_time":0.1258595468,"remaining_time":1.937411712},
{"learn":[6.04825667],"iteration":61,"passed_time":0.1265311629,"remaining_time":1.914294045},
{"learn":[6.015701364],"iteration":62,"passed_time":0.1272287367,"remaining_time":1.89227502},
{"learn":[5.983017466],"iteration":63,"passed_time":0.1279146856,"remaining_time":1.870752277},
{"learn":[5.952258014],"iteration":64,"passed_time":0.1286685916,"remaining_time":1.850848203},
{"learn":[5.920104283],"iteration":65,"passed_time":0.1296176211,"remaining_time":1.834285729},
{"learn":[5.890898682],"iteration":66,"passed_time":0.1302792373,"remaining_time":1.814186992},
{"learn":[5.860352928],"iteration":67,"passed_time":0.1309478115,"remaining_time":1.794755299},
{"learn":[5.837749196],"iteration":68,"passed_time":0.1316186776,"remaining_time":1.775898389},
{"learn":[5.810766099],"iteration":69,"passed_time":0.1322799609,"remaining_time":1.757433766},
{"learn":[5.783353746],"iteration":70,"passed_time":0.1332231574,"remaining_time":1.743159341},
{"learn":[5.762315236],"iteration":71,"passed_time":0.1339689805,"remaining_time":1.726711305},
{"learn":[5.74443798],"iteration":72,"passed_time":0.1348017615,"remaining_time":1.711797712},
{"learn":[5.721104643],"iteration":73,"passed_time":0.1369783998,"remaining_time":1.714081056},
{"learn":[5.699236588],"iteration":74,"passed_time":0.1378247636,"remaining_time":1.699838751},
{"learn":[5.678375367],"iteration":75,"passed_time":0.1388461251,"remaining_time":1.688076573},
{"learn":[5.661417129],"iteration":76,"passed_time":0.1395726994,"remaining_time":1.673059761},
{"learn":[5.640735276],"iteration":77,"passed_time":0.1402428566,"remaining_time":1.657742484},
{"learn":[5.623008181],"iteration":78,"passed_time":0.1409295975,"remaining_time":1.642989358},
{"learn":[5.604955119],"iteration":79,"passed_time":0.1415792139,"remaining_time":1.62816096},
{"learn":[5.588615672],"iteration":80,"passed_time":0.1422065806,"remaining_time":1.613430217},
{"learn":[5.570406363],"iteration":81,"passed_time":0.1429788614,"remaining_time":1.60066579},
{"learn":[5.56264953],"iteration":82,"passed_time":0.1435620617,"remaining_time":1.586101332},
{"learn":[5.550890347],"iteration":83,"passed_time":0.1443761759,"remaining_time":1.574387823},
{"learn":[5.533452113],"iteration":84,"passed_time":0.1450633338,"remaining_time":1.561564123},
{"learn":[5.515794022],"iteration":85,"passed_time":0.1459068227,"remaining_time":1.550684139},
{"learn":[5.499876378],"iteration":86,"passed_time":0.1465254815,"remaining_time":1.537675455},
{"learn":[5.486663721],"iteration":87,"passed_time":0.1471805558,"remaining_time":1.525325761},
{"learn":[5.47222473],"iteration":88,"passed_time":0.1479188791,"remaining_time":1.514090998},
{"learn":[5.457396015],"iteration":89,"passed_time":0.148833534,"remaining_time":1.504872399},
{"learn":[5.446080641],"iteration":90,"passed_time":0.1496420233,"remaining_time":1.494775815},
{"learn":[5.435341269],"iteration":91,"passed_time":0.1513201681,"remaining_time":1.493464268},
{"learn":[5.42340218],"iteration":92,"passed_time":0.1523176549,"remaining_time":1.485506592},
{"learn":[5.414065796],"iteration":93,"passed_time":0.1531100614,"remaining_time":1.475720379},
{"learn":[5.405924794],"iteration":94,"passed_time":0.1539934668,"remaining_time":1.466990394},
{"learn":[5.38988394],"iteration":95,"passed_time":0.1547512067,"remaining_time":1.45724053},
{"learn":[5.379688211],"iteration":96,"passed_time":0.1554349477,"remaining_time":1.446987194},
{"learn":[5.369546245],"iteration":97,"passed_time":0.156245228,"remaining_time":1.438093833},
{"learn":[5.361275064],"iteration":98,"passed_time":0.1569403858,"remaining_time":1.428316036},
{"learn":[5.350131504],"iteration":99,"passed_time":0.1577651249,"remaining_time":1.419886124},
{"learn":[5.342267819],"iteration":100,"passed_time":0.1586197806,"remaining_time":1.411873097},
{"learn":[5.332565944],"iteration":101,"passed_time":0.1593098545,"remaining_time":1.402551464},
{"learn":[5.321761243],"iteration":102,"passed_time":0.160024303,"remaining_time":1.393609707},
{"learn":[5.31175606],"iteration":103,"passed_time":0.1607183358,"remaining_time":1.384650278},
{"learn":[5.302661471],"iteration":104,"passed_time":0.1614389103,"remaining_time":1.376074521},
{"learn":[5.292817645],"iteration":105,"passed_time":0.1621288602,"remaining_time":1.367388689},
{"learn":[5.285481269],"iteration":106,"passed_time":0.1628081432,"remaining_time":1.358763289},
{"learn":[5.2746103],"iteration":107,"passed_time":0.163581883,"remaining_time":1.351065182},
{"learn":[5.266744808],"iteration":108,"passed_time":0.1644329137,"remaining_time":1.344125928},
{"learn":[5.25813932],"iteration":109,"passed_time":0.1652740696,"remaining_time":1.337217472},
{"learn":[5.251787804],"iteration":110,"passed_time":0.1662552226,"remaining_time":1.331539576},
{"learn":[5.246045814],"iteration":111,"passed_time":0.1670811287,"remaining_time":1.324714663},
{"learn":[5.240794967],"iteration":112,"passed_time":0.1677840774,"remaining_time":1.317030767},
{"learn":[5.232474801],"iteration":113,"passed_time":0.168423736,"remaining_time":1.308977457},
{"learn":[5.226199885],"iteration":114,"passed_time":0.1690688934,"remaining_time":1.301095397},
{"learn":[5.217183748],"iteration":115,"passed_time":0.1696857603,"remaining_time":1.293122518},
{"learn":[5.213477702],"iteration":116,"passed_time":0.1701970035,"remaining_time":1.28447824},
{"learn":[5.206246902],"iteration":117,"passed_time":0.1707991615,"remaining_time":1.27665136},
{"learn":[5.20125712],"iteration":118,"passed_time":0.1714723616,"remaining_time":1.269471854},
{"learn":[5.19624085],"iteration":119,"passed_time":0.1722178938,"remaining_time":1.262931221},
{"learn":[5.191264332],"iteration":120,"passed_time":0.1729886746,"remaining_time":1.256669793},
{"learn":[5.189047939],"iteration":121,"passed_time":0.1736201242,"remaining_time":1.249495648},
{"learn":[5.180309822],"iteration":122,"passed_time":0.1743873641,"remaining_time":1.243396084},
{"learn":[5.174580521],"iteration":123,"passed_time":0.1750663131,"remaining_time":1.236758793},
{"learn":[5.170092194],"iteration":124,"passed_time":0.1756244717,"remaining_time":1.229371302},
{"learn":[5.164295537],"iteration":125,"passed_time":0.1762591713,"remaining_time":1.222623141},
{"learn":[5.154745021],"iteration":126,"passed_time":0.1768715802,"remaining_time":1.215818028},
{"learn":[5.151330592],"iteration":127,"passed_time":0.1774846141,"remaining_time":1.209113934},
{"learn":[5.143457595],"iteration":128,"passed_time":0.1781828139,"remaining_time":1.203079309},
{"learn":[5.135890517],"iteration":129,"passed_time":0.1789773034,"remaining_time":1.197771184},
{"learn":[5.12821535],"iteration":130,"passed_time":0.1798200423,"remaining_time":1.192852036},
{"learn":[5.122476081],"iteration":131,"passed_time":0.1808768193,"remaining_time":1.189402115},
{"learn":[5.116625042],"iteration":132,"passed_time":0.1817730154,"remaining_time":1.184941386},
{"learn":[5.109950499],"iteration":133,"passed_time":0.1824961309,"remaining_time":1.179415294},
{"learn":[5.106407172],"iteration":134,"passed_time":0.183169622,"remaining_time":1.173642393},
{"learn":[5.099887437],"iteration":135,"passed_time":0.1838236963,"remaining_time":1.16782113},
{"learn":[5.096488602],"iteration":136,"passed_time":0.1844698548,"remaining_time":1.162025436},
{"learn":[5.093319882],"iteration":137,"passed_time":0.1852478865,"remaining_time":1.157128103},
{"learn":[5.0880159],"iteration":138,"passed_time":0.1859696269,"remaining_time":1.151941358},
{"learn":[5.084269894],"iteration":139,"passed_time":0.1871536113,"remaining_time":1.149657898},
{"learn":[5.081591513],"iteration":140,"passed_time":0.188009266,"remaining_time":1.145389784},
{"learn":[5.077596671],"iteration":141,"passed_time":0.1888314641,"remaining_time":1.140967579},
{"learn":[5.076838149],"iteration":142,"passed_time":0.1893974986,"remaining_time":1.135060534},
{"learn":[5.068597301],"iteration":143,"passed_time":0.1900151565,"remaining_time":1.129534541},
{"learn":[5.058455635],"iteration":144,"passed_time":0.1906479811,"remaining_time":1.124165682},
{"learn":[5.055318395],"iteration":145,"passed_time":0.1913645556,"remaining_time":1.119351579},
{"learn":[5.049165964],"iteration":146,"passed_time":0.1920732962,"remaining_time":1.114547767},
{"learn":[5.046875271],"iteration":147,"passed_time":0.1927008299,"remaining_time":1.109331805},
{"learn":[5.040886565],"iteration":148,"passed_time":0.1937421072,"remaining_time":1.106540491},
{"learn":[5.036653152],"iteration":149,"passed_time":0.1944571397,"remaining_time":1.101923792},
{"learn":[5.030312055],"iteration":150,"passed_time":0.1951390057,"remaining_time":1.09717229},
{"learn":[5.026422148],"iteration":151,"passed_time":0.1958641211,"remaining_time":1.092715623},
{"learn":[5.020742051],"iteration":152,"passed_time":0.1967499424,"remaining_time":1.089197394},
{"learn":[5.016479951],"iteration":153,"passed_time":0.1974446422,"remaining_time":1.084663424},
{"learn":[5.011110629],"iteration":154,"passed_time":0.1980720509,"remaining_time":1.079812149},
{"learn":[5.005858658],"iteration":155,"passed_time":0.1986804599,"remaining_time":1.074912232},
{"learn":[4.997253962],"iteration":156,"passed_time":0.1992841599,"remaining_time":1.070041699},
{"learn":[4.994297907],"iteration":157,"passed_time":0.1999497761,"remaining_time":1.065555136},
{"learn":[4.989210112],"iteration":158,"passed_time":0.2006324331,"remaining_time":1.061206769},
{"learn":[4.983780893],"iteration":159,"passed_time":0.2013039662,"remaining_time":1.056845822},
{"learn":[4.979019566],"iteration":160,"passed_time":0.2018996663,"remaining_time":1.052135528},
{"learn":[4.97510398],"iteration":161,"passed_time":0.2025118252,"remaining_time":1.04756117},
{"learn":[4.972067702],"iteration":162,"passed_time":0.2032560234,"remaining_time":1.043713445},
{"learn":[4.969319224],"iteration":163,"passed_time":0.2038948899,"remaining_time":1.039366634},
{"learn":[4.963856635],"iteration":164,"passed_time":0.2045164657,"remaining_time":1.034977266},
{"learn":[4.959204208],"iteration":165,"passed_time":0.2051095829,"remaining_time":1.030490314},
{"learn":[4.956231943],"iteration":166,"passed_time":0.2057279497,"remaining_time":1.026175941},
{"learn":[4.950262594],"iteration":167,"passed_time":0.2063278998,"remaining_time":1.021814361},
{"learn":[4.944675086],"iteration":168,"passed_time":0.2069219749,"remaining_time":1.017468409},
{"learn":[4.940535137],"iteration":169,"passed_time":0.2075501326,"remaining_time":1.013333},
{"learn":[4.936515399],"iteration":170,"passed_time":0.2082245827,"remaining_time":1.009463035},
{"learn":[4.934761739],"iteration":171,"passed_time":0.2088402825,"remaining_time":1.005347407},
{"learn":[4.930349308],"iteration":172,"passed_time":0.2095811477,"remaining_time":1.001870573},
{"learn":[4.924583195],"iteration":173,"passed_time":0.2103850121,"remaining_time":0.9987242529},
{"learn":[4.918579534],"iteration":174,"passed_time":0.2111934594,"remaining_time":0.9956263087},
{"learn":[4.915185203],"iteration":175,"passed_time":0.2121532387,"remaining_time":0.9932628904},
{"learn":[4.912272193],"iteration":176,"passed_time":0.2128996459,"remaining_time":0.9899232121},
{"learn":[4.910880244],"iteration":177,"passed_time":0.2134812212,"remaining_time":0.985851482},
{"learn":[4.90543088],"iteration":178,"passed_time":0.2142964194,"remaining_time":0.9828902811},
{"learn":[4.903769016],"iteration":179,"passed_time":0.2149367019,"remaining_time":0.9791560865},
{"learn":[4.898648075],"iteration":180,"passed_time":0.215760941,"remaining_time":0.9762884569},
{"learn":[4.895120403],"iteration":181,"passed_time":0.2164187653,"remaining_time":0.9726953299},
{"learn":[4.890924012],"iteration":182,"passed_time":0.21704834,"remaining_time":0.9690081627},
{"learn":[4.888233323],"iteration":183,"passed_time":0.2176612069,"remaining_time":0.9652801349},
{"learn":[4.88588592],"iteration":184,"passed_time":0.2182803657,"remaining_time":0.961613503},
{"learn":[4.879855054],"iteration":185,"passed_time":0.2188972325,"remaining_time":0.9579696091},
{"learn":[4.87319666],"iteration":186,"passed_time":0.2195658077,"remaining_time":0.9545828966},
{"learn":[4.871883809],"iteration":187,"passed_time":0.2201895915,"remaining_time":0.9510316397},
{"learn":[4.869688873],"iteration":188,"passed_time":0.2208097493,"remaining_time":0.9474958024},
{"learn":[4.866073223],"iteration":189,"passed_time":0.2214184912,"remaining_time":0.9439419888},
{"learn":[4.860190342],"iteration":190,"passed_time":0.2220761075,"remaining_time":0.9406260261},
{"learn":[4.857795544],"iteration":191,"passed_time":0.2226805165,"remaining_time":0.9371138404},
{"learn":[4.855497195],"iteration":192,"passed_time":0.2234090069,"remaining_time":0.9341506143},
{"learn":[4.854989776],"iteration":193,"passed_time":0.2237345856,"remaining_time":0.9295364741},
{"learn":[4.850957867],"iteration":194,"passed_time":0.2246436566,"remaining_time":0.927375095},
{"learn":[4.845352962],"iteration":195,"passed_time":0.2253403144,"remaining_time":0.924355167},
{"learn":[4.84012301],"iteration":196,"passed_time":0.2261346788,"remaining_time":0.921757092},
{"learn":[4.838740737],"iteration":197,"passed_time":0.2273227051,"remaining_time":0.9207717653},
{"learn":[4.835929715],"iteration":198,"passed_time":0.2281880267,"remaining_time":0.9184854743},
{"learn":[4.832280742],"iteration":199,"passed_time":0.2289374328,"remaining_time":0.9157497312},
{"learn":[4.826074424],"iteration":200,"passed_time":0.2299252537,"remaining_time":0.9139814812},
{"learn":[4.821474041],"iteration":201,"passed_time":0.2306912016,"remaining_time":0.9113444499},
{"learn":[4.816239764],"iteration":202,"passed_time":0.2314886911,"remaining_time":0.9088496885},
{"learn":[4.812270451],"iteration":203,"passed_time":0.2325916765,"remaining_time":0.9075636003},
{"learn":[4.809535566],"iteration":204,"passed_time":0.2334228315,"remaining_time":0.905225127},
{"learn":[4.806141245],"iteration":205,"passed_time":0.2343157367,"remaining_time":0.9031392957},
{"learn":[4.801317791],"iteration":206,"passed_time":0.2349483113,"remaining_time":0.9000676853},
{"learn":[4.798988268],"iteration":207,"passed_time":0.2356888015,"remaining_time":0.8974304365},
{"learn":[4.79414868],"iteration":208,"passed_time":0.2362969185,"remaining_time":0.894310347},
{"learn":[4.790356382],"iteration":209,"passed_time":0.2370405746,"remaining_time":0.8917240665},
{"learn":[4.786346419],"iteration":210,"passed_time":0.2376379837,"remaining_time":0.8886083847},
{"learn":[4.783753705],"iteration":211,"passed_time":0.2382715594,"remaining_time":0.8856508905},
{"learn":[4.779419316],"iteration":212,"passed_time":0.2390068826,"remaining_time":0.8830911579},
{"learn":[4.774892356],"iteration":213,"passed_time":0.2398292888,"remaining_time":0.8808683223},
{"learn":[4.773666942],"iteration":214,"passed_time":0.2408876498,"remaining_time":0.8795200236},
{"learn":[4.768973033],"iteration":215,"passed_time":0.2422460898,"remaining_time":0.8792635852},
{"learn":[4.766600919],"iteration":216,"passed_time":0.2432062021,"remaining_time":0.8775597062},
{"learn":[4.761186971],"iteration":217,"passed_time":0.2440314412,"remaining_time":0.8753788395},
{"learn":[4.758141908],"iteration":218,"passed_time":0.2446714737,"remaining_time":0.8725498675},
{"learn":[4.754832398],"iteration":219,"passed_time":0.2454261728,"remaining_time":0.8701473398},
{"learn":[4.754304417],"iteration":220,"passed_time":0.2461005388,"remaining_time":0.86747656},
{"learn":[4.749143482],"iteration":221,"passed_time":0.246923445,"remaining_time":0.8653443251},
{"learn":[4.74623948],"iteration":222,"passed_time":0.2480914715,"remaining_time":0.864426338},
{"learn":[4.742023239],"iteration":223,"passed_time":0.2488000041,"remaining_time":0.8619143001},
{"learn":[4.739411587],"iteration":224,"passed_time":0.2495973686,"remaining_time":0.8597242696},
{"learn":[4.735492257],"iteration":225,"passed_time":0.2502171104,"remaining_time":0.8569382454},
{"learn":[4.73183112],"iteration":226,"passed_time":0.250932351,"remaining_time":0.8544965079},
{"learn":[4.730547597],"iteration":227,"passed_time":0.2515987591,"remaining_time":0.8519045704},
{"learn":[4.727185831],"iteration":228,"passed_time":0.2521771685,"remaining_time":0.8490331743},
{"learn":[4.72418831],"iteration":229,"passed_time":0.252971783,"remaining_time":0.8469055343},
{"learn":[4.72148412],"iteration":230,"passed_time":0.2551566291,"remaining_time":0.8494175228},
{"learn":[4.719442057],"iteration":231,"passed_time":0.2561824495,"remaining_time":0.8480522467},
{"learn":[4.71746484],"iteration":232,"passed_time":0.2572518934,"remaining_time":0.846833486},
{"learn":[4.712123474],"iteration":233,"passed_time":0.257959718,"remaining_time":0.8444322394},
{"learn":[4.706628849],"iteration":234,"passed_time":0.2588200407,"remaining_time":0.8425418345},
{"learn":[4.701418465],"iteration":235,"passed_time":0.2594499483,"remaining_time":0.8399142395},
{"learn":[4.698429346],"iteration":236,"passed_time":0.260155439,"remaining_time":0.8375468353},
{"learn":[4.696104112],"iteration":237,"passed_time":0.261136926,"remaining_time":0.8360770488},
{"learn":[4.691850323],"iteration":238,"passed_time":0.2618646254,"remaining_time":0.8338032633},
{"learn":[4.686547932],"iteration":239,"passed_time":0.2626189074,"remaining_time":0.8316265402},
{"learn":[4.684212802],"iteration":240,"passed_time":0.2634896879,"remaining_time":0.8298285192},
{"learn":[4.683686742],"iteration":241,"passed_time":0.2651148324,"remaining_time":0.830401004},
{"learn":[4.681660001],"iteration":242,"passed_time":0.2657643658,"remaining_time":0.827916152},
{"learn":[4.679600608],"iteration":243,"passed_time":0.2664782734,"remaining_time":0.8256457979},
{"learn":[4.678536726],"iteration":244,"passed_time":0.2670894733,"remaining_time":0.8230716422},
{"learn":[4.673771121],"iteration":245,"passed_time":0.2677457976,"remaining_time":0.8206517537},
{"learn":[4.672607833],"iteration":246,"passed_time":0.2683882481,"remaining_time":0.8182038496},
{"learn":[4.669570198],"iteration":247,"passed_time":0.2689935311,"remaining_time":0.8156578041},
{"learn":[4.665766046],"iteration":248,"passed_time":0.2698206862,"remaining_time":0.8137965274},
{"learn":[4.662726098],"iteration":249,"passed_time":0.2710180454,"remaining_time":0.8130541361},
{"learn":[4.660135105],"iteration":250,"passed_time":0.2720513647,"remaining_time":0.8118186142},
{"learn":[4.659757754],"iteration":251,"passed_time":0.2729998522,"remaining_time":0.8103328945},
{"learn":[4.657233188],"iteration":252,"passed_time":0.2739615474,"remaining_time":0.8088904187},
{"learn":[4.654407093],"iteration":253,"passed_time":0.2747172464,"remaining_time":0.8068467159},
{"learn":[4.651418934],"iteration":254,"passed_time":0.2754401119,"remaining_time":0.8047171896},
{"learn":[4.643118293],"iteration":255,"passed_time":0.2761423946,"remaining_time":0.8025388343},
{"learn":[4.639261915],"iteration":256,"passed_time":0.2768465103,"remaining_time":0.8003772652},
{"learn":[4.637282776],"iteration":257,"passed_time":0.2775361262,"remaining_time":0.7981852931},
{"learn":[4.634448336],"iteration":258,"passed_time":0.2781962424,"remaining_time":0.7959205238},
{"learn":[4.631331654],"iteration":259,"passed_time":0.2788157343,"remaining_time":0.7935524744},
{"learn":[4.628581358],"iteration":260,"passed_time":0.2795101841,"remaining_time":0.7914100614},
{"learn":[4.626421751],"iteration":261,"passed_time":0.2803889635,"remaining_time":0.78979792},
{"learn":[4.621886602],"iteration":262,"passed_time":0.2812602849,"remaining_time":0.7881704562},
{"learn":[4.619116604],"iteration":263,"passed_time":0.2820346497,"remaining_time":0.7862784173},
{"learn":[4.614721439],"iteration":264,"passed_time":0.2829103051,"remaining_time":0.7846757519},
{"learn":[4.612235456],"iteration":265,"passed_time":0.2838198351,"remaining_time":0.7831720261},
{"learn":[4.607836546],"iteration":266,"passed_time":0.2849846537,"remaining_time":0.7823735998},
{"learn":[4.60713316],"iteration":267,"passed_time":0.2861089718,"remaining_time":0.7814618185},
{"learn":[4.606821715],"iteration":268,"passed_time":0.2871323753,"remaining_time":0.7802742243},
{"learn":[4.606297807],"iteration":269,"passed_time":0.2880100717,"remaining_time":0.7786938975},
{"learn":[4.602081065],"iteration":270,"passed_time":0.2887944773,"remaining_time":0.7768678006},
{"learn":[4.600164398],"iteration":271,"passed_time":0.2894652604,"remaining_time":0.7747452559},
{"learn":[4.597298036],"iteration":272,"passed_time":0.2901296677,"remaining_time":0.7726163677},
{"learn":[4.592506881],"iteration":273,"passed_time":0.2911131136,"remaining_time":0.7713435055},
{"learn":[4.590468795],"iteration":274,"passed_time":0.2956042213,"remaining_time":0.7793202197},
{"learn":[4.587482352],"iteration":275,"passed_time":0.2964133766,"remaining_time":0.7775481327},
{"learn":[4.584851946],"iteration":276,"passed_time":0.2971456169,"remaining_time":0.7755822419},
{"learn":[4.580775747],"iteration":277,"passed_time":0.297816524,"remaining_time":0.7734659365},
{"learn":[4.57915937],"iteration":278,"passed_time":0.2985274316,"remaining_time":0.7714633627},
{"learn":[4.572036268],"iteration":279,"passed_time":0.2994710441,"remaining_time":0.7700683992},
{"learn":[4.568662367],"iteration":280,"passed_time":0.300162369,"remaining_time":0.768031115},
{"learn":[4.568259984],"iteration":281,"passed_time":0.3010456073,"remaining_time":0.7664920073},
{"learn":[4.564420416],"iteration":282,"passed_time":0.3026280864,"remaining_time":0.7667291093},
{"learn":[4.560925453],"iteration":283,"passed_time":0.303339702,"remaining_time":0.7647578402},
{"learn":[4.557730021],"iteration":284,"passed_time":0.303939278,"remaining_time":0.7625143291},
{"learn":[4.557449747],"iteration":285,"passed_time":0.3045441451,"remaining_time":0.760295523},
{"learn":[4.552253298],"iteration":286,"passed_time":0.3052220951,"remaining_time":0.7582695254},
{"learn":[4.550027089],"iteration":287,"passed_time":0.3059539604,"remaining_time":0.7563861799},
{"learn":[4.546622384],"iteration":288,"passed_time":0.3091197105,"remaining_time":0.7604986651},
{"learn":[4.54370183],"iteration":289,"passed_time":0.310067406,"remaining_time":0.7591305458},
{"learn":[4.539129752],"iteration":290,"passed_time":0.3110295183,"remaining_time":0.7578004415},
{"learn":[4.532289234],"iteration":291,"passed_time":0.3118600483,"remaining_time":0.7561538158},
{"learn":[4.52762352],"iteration":292,"passed_time":0.3126594127,"remaining_time":0.7544375591},
{"learn":[4.524694054],"iteration":293,"passed_time":0.3148520508,"remaining_time":0.7560732919},
{"learn":[4.522732074],"iteration":294,"passed_time":0.3157207053,"remaining_time":0.7545189736},
{"learn":[4.518700772],"iteration":295,"passed_time":0.3168602312,"remaining_time":0.7536135228},
{"learn":[4.516117496],"iteration":296,"passed_time":0.3179188002,"remaining_time":0.7525148705},
{"learn":[4.514230136],"iteration":297,"passed_time":0.3189346618,"remaining_time":0.7513158811},
{"learn":[4.513060994],"iteration":298,"passed_time":0.3199378155,"remaining_time":0.7500883233},
{"learn":[4.508268618],"iteration":299,"passed_time":0.3210957162,"remaining_time":0.7492233378},
{"learn":[4.50594495],"iteration":300,"passed_time":0.3221058278,"remaining_time":0.7480132015},
{"learn":[4.502352707],"iteration":301,"passed_time":0.3231348552,"remaining_time":0.7468481091},
{"learn":[4.500025772],"iteration":302,"passed_time":0.3241462999,"remaining_time":0.7456434686},
{"learn":[4.499412623],"iteration":303,"passed_time":0.3251306618,"remaining_time":0.7443780942},
{"learn":[4.495162197],"iteration":304,"passed_time":0.3261255657,"remaining_time":0.7431385841},
{"learn":[4.493701353],"iteration":305,"passed_time":0.3272612177,"remaining_time":0.7422198858},
{"learn":[4.487956411],"iteration":306,"passed_time":0.3283097038,"remaining_time":0.7411030122},
{"learn":[4.484224026],"iteration":307,"passed_time":0.3292907328,"remaining_time":0.7398350231},
{"learn":[4.478540598],"iteration":308,"passed_time":0.3303104283,"remaining_time":0.7386553592},
{"learn":[4.474601947],"iteration":309,"passed_time":0.3313154981,"remaining_time":0.7374441731},
{"learn":[4.468424324],"iteration":310,"passed_time":0.332753938,"remaining_time":0.7371944158},
{"learn":[4.4641845],"iteration":311,"passed_time":0.333586177,"remaining_time":0.7356002878},
{"learn":[4.460735098],"iteration":312,"passed_time":0.3351975307,"remaining_time":0.7357210978},
{"learn":[4.457313497],"iteration":313,"passed_time":0.3359848953,"remaining_time":0.7340306949},
{"learn":[4.456797356],"iteration":314,"passed_time":0.3367548431,"remaining_time":0.7323081509},
{"learn":[4.454349127],"iteration":315,"passed_time":0.3375537496,"remaining_time":0.7306543187},
{"learn":[4.454093256],"iteration":316,"passed_time":0.3383314053,"remaining_time":0.728960094},
{"learn":[4.451987388],"iteration":317,"passed_time":0.3393827664,"remaining_time":0.7278586373},
{"learn":[4.445053512],"iteration":318,"passed_time":0.3404418774,"remaining_time":0.7267740392},
{"learn":[4.443318441],"iteration":319,"passed_time":0.3414993214,"remaining_time":0.725686058},
{"learn":[4.441587145],"iteration":320,"passed_time":0.3424651006,"remaining_time":0.7244043717},
{"learn":[4.437287481],"iteration":321,"passed_time":0.3436695017,"remaining_time":0.7236270874},
{"learn":[4.433519981],"iteration":322,"passed_time":0.3447152379,"remaining_time":0.7225146007},
{"learn":[4.432560068],"iteration":323,"passed_time":0.3455419769,"remaining_time":0.7209456062},
{"learn":[4.429913294],"iteration":324,"passed_time":0.3462896331,"remaining_time":0.7192169302},
{"learn":[4.427698653],"iteration":325,"passed_time":0.3471884542,"remaining_time":0.717806804},
{"learn":[4.424096209],"iteration":326,"passed_time":0.3479160275,"remaining_time":0.7160473595},
{"learn":[4.419729904],"iteration":327,"passed_time":0.3485968515,"remaining_time":0.7141984276},
{"learn":[4.416968943],"iteration":328,"passed_time":0.3493866741,"remaining_time":0.7125789007},
{"learn":[4.415355971],"iteration":329,"passed_time":0.350154289,"remaining_time":0.7109193139},
{"learn":[4.415108567],"iteration":330,"passed_time":0.3509149459,"remaining_time":0.7092510538},
{"learn":[4.414133445],"iteration":331,"passed_time":0.3515917279,"remaining_time":0.7074195008},
{"learn":[4.412518066],"iteration":332,"passed_time":0.3523487179,"remaining_time":0.7057555401},
{"learn":[4.412174468],"iteration":333,"passed_time":0.3543774821,"remaining_time":0.7066329434},
{"learn":[4.410210838],"iteration":334,"passed_time":0.3554375511,"remaining_time":0.7055700641},
{"learn":[4.407117122],"iteration":335,"passed_time":0.3565491194,"remaining_time":0.704608974},
{"learn":[4.400820858],"iteration":336,"passed_time":0.3573981082,"remaining_time":0.7031304027},
{"learn":[4.397882608],"iteration":337,"passed_time":0.3585155104,"remaining_time":0.7021812659},
{"learn":[4.395843573],"iteration":338,"passed_time":0.3593992487,"remaining_time":0.7007755262},
{"learn":[4.391753018],"iteration":339,"passed_time":0.3606239415,"remaining_time":0.70003471},
{"learn":[4.389301531],"iteration":340,"passed_time":0.3613774316,"remaining_time":0.6983804322},
{"learn":[4.387409259],"iteration":341,"passed_time":0.3620845472,"remaining_time":0.696642199},
{"learn":[4.384724508],"iteration":342,"passed_time":0.3628477031,"remaining_time":0.6950173205},
{"learn":[4.37878243],"iteration":343,"passed_time":0.3635489438,"remaining_time":0.6932793813},
{"learn":[4.374991277],"iteration":344,"passed_time":0.3641745606,"remaining_time":0.6914038759},
{"learn":[4.372750344],"iteration":345,"passed_time":0.364750261,"remaining_time":0.6894412447},
{"learn":[4.370497422],"iteration":346,"passed_time":0.365350086,"remaining_time":0.6875320063},
{"learn":[4.365785756],"iteration":347,"passed_time":0.3660265771,"remaining_time":0.6857739318},
{"learn":[4.364562678],"iteration":348,"passed_time":0.3666771935,"remaining_time":0.6839737907},
{"learn":[4.361705552],"iteration":349,"passed_time":0.3673434767,"remaining_time":0.6822093138},
{"learn":[4.357308115],"iteration":350,"passed_time":0.3681890485,"remaining_time":0.6807825996},
{"learn":[4.3559015],"iteration":351,"passed_time":0.3695827391,"remaining_time":0.6803682242},
{"learn":[4.351542306],"iteration":352,"passed_time":0.3706668077,"remaining_time":0.6793808062},
{"learn":[4.347455916],"iteration":353,"passed_time":0.3715942535,"remaining_time":0.6781070275},
{"learn":[4.347205755],"iteration":354,"passed_time":0.3725598237,"remaining_time":0.6769044684},
{"learn":[4.345826342],"iteration":355,"passed_time":0.3736659341,"remaining_time":0.6759574762},
{"learn":[4.342587945],"iteration":356,"passed_time":0.3747479198,"remaining_time":0.6749661412},
{"learn":[4.338900645],"iteration":357,"passed_time":0.375560617,"remaining_time":0.6734913858},
{"learn":[4.337610384],"iteration":358,"passed_time":0.3763043992,"remaining_time":0.6718972698},
{"learn":[4.3333725],"iteration":359,"passed_time":0.3773091769,"remaining_time":0.67077187},
{"learn":[4.3285432],"iteration":360,"passed_time":0.3781177502,"remaining_time":0.6692998404},
{"learn":[4.322494549],"iteration":361,"passed_time":0.3788449496,"remaining_time":0.6676880603},
{"learn":[4.319075563],"iteration":362,"passed_time":0.3797568535,"remaining_time":0.6664052774},
{"learn":[4.313459231],"iteration":363,"passed_time":0.3805297183,"remaining_time":0.6648815957},
{"learn":[4.307760286],"iteration":364,"passed_time":0.3812428749,"remaining_time":0.6632581522},
{"learn":[4.307447422],"iteration":365,"passed_time":0.3824882334,"remaining_time":0.6625615846},
{"learn":[4.303387404],"iteration":366,"passed_time":0.3835458034,"remaining_time":0.6615381296},
{"learn":[4.300838317],"iteration":367,"passed_time":0.3847079961,"remaining_time":0.6606941671},
{"learn":[4.296987048],"iteration":368,"passed_time":0.385767398,"remaining_time":0.6596727051},
{"learn":[4.293469607],"iteration":369,"passed_time":0.3867840936,"remaining_time":0.6585783215},
{"learn":[4.291014224],"iteration":370,"passed_time":0.3876699979,"remaining_time":0.657262611},
{"learn":[4.288255951],"iteration":371,"passed_time":0.3887047762,"remaining_time":0.6562005362},
{"learn":[4.284594658],"iteration":372,"passed_time":0.3896230561,"remaining_time":0.6549427779},
{"learn":[4.282719988],"iteration":373,"passed_time":0.3905987522,"remaining_time":0.6537829381},
{"learn":[4.28053137],"iteration":374,"passed_time":0.3914155324,"remaining_time":0.6523592206},
{"learn":[4.276959662],"iteration":375,"passed_time":0.3923388542,"remaining_time":0.6511155452},
{"learn":[4.27165626],"iteration":376,"passed_time":0.3931309687,"remaining_time":0.6496567466},
{"learn":[4.267827983],"iteration":377,"passed_time":0.3938961246,"remaining_time":0.648157115},
{"learn":[4.263554923],"iteration":378,"passed_time":0.3946081981,"remaining_time":0.6465743827},
{"learn":[4.258755259],"iteration":379,"passed_time":0.3957024337,"remaining_time":0.6456197602},
{"learn":[4.254342717],"iteration":380,"passed_time":0.3969461672,"remaining_time":0.6449072901},
{"learn":[4.25305819],"iteration":381,"passed_time":0.3979565289,"remaining_time":0.6438144891},
{"learn":[4.250702604],"iteration":382,"passed_time":0.399078389,"remaining_time":0.642901739},
{"learn":[4.244987098],"iteration":383,"passed_time":0.3998836704,"remaining_time":0.6414800546},
{"learn":[4.240307103],"iteration":384,"passed_time":0.4008539486,"remaining_time":0.6403251386},
{"learn":[4.239032658],"iteration":385,"passed_time":0.4016161465,"remaining_time":0.6388401915},
{"learn":[4.233663544],"iteration":386,"passed_time":0.4023594697,"remaining_time":0.6373290824},
{"learn":[4.233123673],"iteration":387,"passed_time":0.4031694169,"remaining_time":0.6359270185},
{"learn":[4.231348216],"iteration":388,"passed_time":0.404147737,"remaining_time":0.6347924609},
{"learn":[4.22984818],"iteration":389,"passed_time":0.4049131859,"remaining_time":0.6333257523},
{"learn":[4.228408102],"iteration":390,"passed_time":0.4059010478,"remaining_time":0.6322090489},
{"learn":[4.227560765],"iteration":391,"passed_time":0.4065583721,"remaining_time":0.6305803323},
{"learn":[4.223269203],"iteration":392,"passed_time":0.407397361,"remaining_time":0.6292371454},
{"learn":[4.219000579],"iteration":393,"passed_time":0.4081108926,"remaining_time":0.6277035556},
{"learn":[4.216634837],"iteration":394,"passed_time":0.4088775075,"remaining_time":0.6262554228},
{"learn":[4.214439047],"iteration":395,"passed_time":0.4095981649,"remaining_time":0.6247406354},
{"learn":[4.209695861],"iteration":396,"passed_time":0.4103596959,"remaining_time":0.623291931},
{"learn":[4.20948213],"iteration":397,"passed_time":0.4110731024,"remaining_time":0.6217738886},
{"learn":[4.205975517],"iteration":398,"passed_time":0.4119973402,"remaining_time":0.6205774473},
{"learn":[4.202514367],"iteration":399,"passed_time":0.4129718683,"remaining_time":0.6194578025},
{"learn":[4.200402966],"iteration":400,"passed_time":0.4151083811,"remaining_time":0.6200746141},
{"learn":[4.196112721],"iteration":401,"passed_time":0.4158832458,"remaining_time":0.6186521916},
{"learn":[4.194770053],"iteration":402,"passed_time":0.4165716117,"remaining_time":0.6171048442},
{"learn":[4.193104546],"iteration":403,"passed_time":0.4173163519,"remaining_time":0.6156449151},
{"learn":[4.190161777],"iteration":404,"passed_time":0.4183592961,"remaining_time":0.6146266202},
{"learn":[4.186491882],"iteration":405,"passed_time":0.4189864548,"remaining_time":0.6129998871},
{"learn":[4.184195905],"iteration":406,"passed_time":0.4196006967,"remaining_time":0.611359246},
{"learn":[4.182773236],"iteration":407,"passed_time":0.4202241884,"remaining_time":0.6097370577},
{"learn":[4.179809116],"iteration":408,"passed_time":0.4208542641,"remaining_time":0.6081292667},
{"learn":[4.179124177],"iteration":409,"passed_time":0.4215032135,"remaining_time":0.6065534048},
{"learn":[4.177906439],"iteration":410,"passed_time":0.422144038,"remaining_time":0.6049704097},
{"learn":[4.17228084],"iteration":411,"passed_time":0.4227843636,"remaining_time":0.6033912762},
{"learn":[4.171016626],"iteration":412,"passed_time":0.4233996054,"remaining_time":0.6017810373},
{"learn":[4.168472838],"iteration":413,"passed_time":0.4240291801,"remaining_time":0.6001958926},
{"learn":[4.164849278],"iteration":414,"passed_time":0.4248776269,"remaining_time":0.5989238837},
{"learn":[4.164584402],"iteration":415,"passed_time":0.4256067833,"remaining_time":0.5974864457},
{"learn":[4.162123635],"iteration":416,"passed_time":0.4262978571,"remaining_time":0.5959991623},
{"learn":[4.160425532],"iteration":417,"passed_time":0.4277808375,"remaining_time":0.5956182953},
{"learn":[4.156640874],"iteration":418,"passed_time":0.4286064516,"remaining_time":0.5943206405},
{"learn":[4.154619387],"iteration":419,"passed_time":0.4293232341,"remaining_time":0.5928749423},
{"learn":[4.152517842],"iteration":420,"passed_time":0.4299969752,"remaining_time":0.5913735122},
{"learn":[4.150622825],"iteration":421,"passed_time":0.4306878821,"remaining_time":0.5898995162},
{"learn":[4.146567908],"iteration":422,"passed_time":0.4313381655,"remaining_time":0.5883738096},
{"learn":[4.144060699],"iteration":423,"passed_time":0.4320479481,"remaining_time":0.5869330615},
{"learn":[4.141016228],"iteration":424,"passed_time":0.4328227288,"remaining_time":0.585583692},
{"learn":[4.13911462],"iteration":425,"passed_time":0.4335055118,"remaining_time":0.5841130605},
{"learn":[4.137180866],"iteration":426,"passed_time":0.4348108695,"remaining_time":0.583481565},
{"learn":[4.133799596],"iteration":427,"passed_time":0.4355409849,"remaining_time":0.5820781387},
{"learn":[4.133317241],"iteration":428,"passed_time":0.4362063931,"remaining_time":0.580591726},
{"learn":[4.13230584],"iteration":429,"passed_time":0.4369913827,"remaining_time":0.5792676469},
{"learn":[4.130390502],"iteration":430,"passed_time":0.4391303544,"remaining_time":0.579733577},
{"learn":[4.130051533],"iteration":431,"passed_time":0.4399588855,"remaining_time":0.5784644605},
{"learn":[4.128010037],"iteration":432,"passed_time":0.440676668,"remaining_time":0.5770523574},
{"learn":[4.124030985],"iteration":433,"passed_time":0.4413475761,"remaining_time":0.5755823228},
{"learn":[4.120271582],"iteration":434,"passed_time":0.4421232329,"remaining_time":0.5742520151},
{"learn":[4.116189931],"iteration":435,"passed_time":0.4428853478,"remaining_time":0.5729067343},
{"learn":[4.115096603],"iteration":436,"passed_time":0.4438615849,"remaining_time":0.5718399823},
{"learn":[4.112557367],"iteration":437,"passed_time":0.4446926989,"remaining_time":0.5705874356},
{"learn":[4.110014909],"iteration":438,"passed_time":0.445591604,"remaining_time":0.5694234393},
{"learn":[4.109342255],"iteration":439,"passed_time":0.4470496257,"remaining_time":0.5689722509},
{"learn":[4.106305196],"iteration":440,"passed_time":0.4478256575,"remaining_time":0.5676520239},
{"learn":[4.105987822],"iteration":441,"passed_time":0.4485036065,"remaining_time":0.5662104353},
{"learn":[4.105460919],"iteration":442,"passed_time":0.4537939955,"remaining_time":0.5705716829},
{"learn":[4.102610368],"iteration":443,"passed_time":0.4546087768,"remaining_time":0.5692848646},
{"learn":[4.097703837],"iteration":444,"passed_time":0.4553405591,"remaining_time":0.5678966523},
{"learn":[4.095838419],"iteration":445,"passed_time":0.4563517547,"remaining_time":0.5668584577},
{"learn":[4.095354848],"iteration":446,"passed_time":0.4581981053,"remaining_time":0.5668535844},
{"learn":[4.094830156],"iteration":447,"passed_time":0.4589399285,"remaining_time":0.5654795548},
{"learn":[4.092992402],"iteration":448,"passed_time":0.4604337007,"remaining_time":0.5650311116},
{"learn":[4.091250899],"iteration":449,"passed_time":0.4611455663,"remaining_time":0.5636223588},
{"learn":[4.087384668],"iteration":450,"passed_time":0.4620143458,"remaining_time":0.562407707},
{"learn":[4.085648343],"iteration":451,"passed_time":0.4628123773,"remaining_time":0.5611088114},
{"learn":[4.081973638],"iteration":452,"passed_time":0.4635623674,"remaining_time":0.5597541169},
{"learn":[4.081647843],"iteration":453,"passed_time":0.4642374414,"remaining_time":0.5583119891},
{"learn":[4.07935867],"iteration":454,"passed_time":0.4650738054,"remaining_time":0.5570664262},
{"learn":[4.076969011],"iteration":455,"passed_time":0.4658025458,"remaining_time":0.5556942651},
{"learn":[4.075461496],"iteration":456,"passed_time":0.4665572018,"remaining_time":0.5543557124},
{"learn":[4.07362437],"iteration":457,"passed_time":0.4672731503,"remaining_time":0.5529739028},
{"learn":[4.070481572],"iteration":458,"passed_time":0.4679505163,"remaining_time":0.5515495193},
{"learn":[4.066497525],"iteration":459,"passed_time":0.4686650909,"remaining_time":0.5501720632},
{"learn":[4.064181418],"iteration":460,"passed_time":0.4693884983,"remaining_time":0.5488078104},
{"learn":[4.062596747],"iteration":461,"passed_time":0.4700350318,"remaining_time":0.5473568119},
{"learn":[4.060004274],"iteration":462,"passed_time":0.4707591892,"remaining_time":0.5459993188},
{"learn":[4.058144041],"iteration":463,"passed_time":0.4715825113,"remaining_time":0.5447591079},
{"learn":[4.055654465],"iteration":464,"passed_time":0.4725293738,"remaining_time":0.5436628279},
{"learn":[4.055211713],"iteration":465,"passed_time":0.4731587815,"remaining_time":0.5422034105},
{"learn":[4.052435892],"iteration":466,"passed_time":0.4738214397,"remaining_time":0.5407854976},
{"learn":[4.048994608],"iteration":467,"passed_time":0.474478347,"remaining_time":0.5393642748},
{"learn":[4.04734987],"iteration":468,"passed_time":0.4751300054,"remaining_time":0.5379403686},
{"learn":[4.045100767],"iteration":469,"passed_time":0.4757741639,"remaining_time":0.5365112912},
{"learn":[4.042274854],"iteration":470,"passed_time":0.4764182804,"remaining_time":0.5350854996},
{"learn":[4.040355781],"iteration":471,"passed_time":0.4770813556,"remaining_time":0.5336842283},
{"learn":[4.037705386],"iteration":472,"passed_time":0.4777071393,"remaining_time":0.5322445295},
{"learn":[4.03576286],"iteration":473,"passed_time":0.4783481729,"remaining_time":0.5308251876},
{"learn":[4.03547339],"iteration":474,"passed_time":0.4790290809,"remaining_time":0.5294531946},
{"learn":[4.032880425],"iteration":475,"passed_time":0.4796581975,"remaining_time":0.5280270914},
{"learn":[4.031104345],"iteration":476,"passed_time":0.4802653975,"remaining_time":0.5265802996},
{"learn":[4.029694371],"iteration":477,"passed_time":0.480981388,"remaining_time":0.5252558254},
{"learn":[4.026166057],"iteration":478,"passed_time":0.481740628,"remaining_time":0.5239809336},
{"learn":[4.025019599],"iteration":479,"passed_time":0.4824333278,"remaining_time":0.5226361052},
{"learn":[4.024892847],"iteration":480,"passed_time":0.4831914008,"remaining_time":0.521364526},
{"learn":[4.021315703],"iteration":481,"passed_time":0.483858976,"remaining_time":0.5199978207},
{"learn":[4.019634382],"iteration":482,"passed_time":0.4845809664,"remaining_time":0.518692256},
{"learn":[4.019492221],"iteration":483,"passed_time":0.485222124,"remaining_time":0.5173029256},
{"learn":[4.014464733],"iteration":484,"passed_time":0.485977822,"remaining_time":0.5160383058},
{"learn":[4.010937035],"iteration":485,"passed_time":0.4868441025,"remaining_time":0.5148927339},
{"learn":[4.009127912],"iteration":486,"passed_time":0.4877072161,"remaining_time":0.513744973},
{"learn":[4.007383691],"iteration":487,"passed_time":0.4884367065,"remaining_time":0.5124581838},
{"learn":[4.005353294],"iteration":488,"passed_time":0.4892459878,"remaining_time":0.5112570547},
{"learn":[4.00305974],"iteration":489,"passed_time":0.4900548111,"remaining_time":0.5100570483},
{"learn":[4.00114142],"iteration":490,"passed_time":0.4908809251,"remaining_time":0.5088765599},
{"learn":[3.998650727],"iteration":491,"passed_time":0.4916531649,"remaining_time":0.5076418857},
{"learn":[3.998433192],"iteration":492,"passed_time":0.4922807396,"remaining_time":0.5062603144},
{"learn":[3.993672123],"iteration":493,"passed_time":0.4930184379,"remaining_time":0.5049945943},
{"learn":[3.992439778],"iteration":494,"passed_time":0.4936705123,"remaining_time":0.5036436539},
{"learn":[3.991808769],"iteration":495,"passed_time":0.494445752,"remaining_time":0.5024206835},
{"learn":[3.987254059],"iteration":496,"passed_time":0.4952167418,"remaining_time":0.5011952135},
{"learn":[3.985532773],"iteration":497,"passed_time":0.4960303561,"remaining_time":0.5000145356},
{"learn":[3.983933542],"iteration":498,"passed_time":0.4968205956,"remaining_time":0.4988118605},
{"learn":[3.983074398],"iteration":499,"passed_time":0.4976164601,"remaining_time":0.4976164601},
{"learn":[3.978217086],"iteration":500,"passed_time":0.4984829066,"remaining_time":0.4964929549},
{"learn":[3.974475713],"iteration":501,"passed_time":0.499211355,"remaining_time":0.4952335753},
{"learn":[3.97290018],"iteration":502,"passed_time":0.4999722609,"remaining_time":0.4940083771},
{"learn":[3.971171035],"iteration":503,"passed_time":0.5007518346,"remaining_time":0.4928033928},
{"learn":[3.969761399],"iteration":504,"passed_time":0.5015911575,"remaining_time":0.4916586594},
{"learn":[3.967645954],"iteration":505,"passed_time":0.5025269781,"remaining_time":0.4906093423},
{"learn":[3.964662954],"iteration":506,"passed_time":0.5034042585,"remaining_time":0.4895035492},
{"learn":[3.962163047],"iteration":507,"passed_time":0.5041622485,"remaining_time":0.4882831226},
{"learn":[3.961869453],"iteration":508,"passed_time":0.5049253214,"remaining_time":0.4870694162},
{"learn":[3.961184907],"iteration":509,"passed_time":0.5056601037,"remaining_time":0.4858302957},
{"learn":[3.956687047],"iteration":510,"passed_time":0.5064409684,"remaining_time":0.4846372476},
{"learn":[3.951890838],"iteration":511,"passed_time":0.5071949164,"remaining_time":0.4834201547},
{"learn":[3.948195368],"iteration":512,"passed_time":0.5079893649,"remaining_time":0.4822433152},
{"learn":[3.947820979],"iteration":513,"passed_time":0.5087317711,"remaining_time":0.4810187563},
{"learn":[3.946349324],"iteration":514,"passed_time":0.5103390828,"remaining_time":0.4806105926},
{"learn":[3.944144171],"iteration":515,"passed_time":0.5109871153,"remaining_time":0.4792979919},
{"learn":[3.943392958],"iteration":516,"passed_time":0.5117422713,"remaining_time":0.4780880407},
{"learn":[3.943185133],"iteration":517,"passed_time":0.5124577198,"remaining_time":0.4768428976},
{"learn":[3.940702624],"iteration":518,"passed_time":0.513277793,"remaining_time":0.47569676},
{"learn":[3.937601716],"iteration":519,"passed_time":0.5139504091,"remaining_time":0.4744157622},
{"learn":[3.936092862],"iteration":520,"passed_time":0.5147641483,"remaining_time":0.4732668466},
{"learn":[3.933739588],"iteration":521,"passed_time":0.5155133044,"remaining_time":0.4720600757},
{"learn":[3.932155806],"iteration":522,"passed_time":0.5162979601,"remaining_time":0.470887432},
{"learn":[3.930793716],"iteration":523,"passed_time":0.5171842393,"remaining_time":0.4698085838},
{"learn":[3.92979767],"iteration":524,"passed_time":0.5182058098,"remaining_time":0.4688528756},
{"learn":[3.925883186],"iteration":525,"passed_time":0.5188974257,"remaining_time":0.4675995813},
{"learn":[3.924565889],"iteration":526,"passed_time":0.5195362502,"remaining_time":0.4663010367},
{"learn":[3.922124297],"iteration":527,"passed_time":0.5201664919,"remaining_time":0.4649973185},
{"learn":[3.921749406],"iteration":528,"passed_time":0.5208026915,"remaining_time":0.4637014512},
{"learn":[3.918414481],"iteration":529,"passed_time":0.5214253083,"remaining_time":0.4623960281},
{"learn":[3.917812979],"iteration":530,"passed_time":0.5220354672,"remaining_time":0.4610821735},
{"learn":[3.915019192],"iteration":531,"passed_time":0.522733291,"remaining_time":0.459848083},
{"learn":[3.913733511],"iteration":532,"passed_time":0.5234593644,"remaining_time":0.4586407564},
{"learn":[3.910802325],"iteration":533,"passed_time":0.5240485236,"remaining_time":0.4573157528},
{"learn":[3.908819755],"iteration":534,"passed_time":0.5246591405,"remaining_time":0.4560121502},
{"learn":[3.907315688],"iteration":535,"passed_time":0.5252809243,"remaining_time":0.4547208001},
{"learn":[3.903410407],"iteration":536,"passed_time":0.5258876663,"remaining_time":0.4534189748},
{"learn":[3.900306371],"iteration":537,"passed_time":0.5264989922,"remaining_time":0.4521236699},
{"learn":[3.898122858],"iteration":538,"passed_time":0.5271218169,"remaining_time":0.4508407377},
{"learn":[3.895347876],"iteration":539,"passed_time":0.5277638084,"remaining_time":0.4495765776},
{"learn":[3.8906818],"iteration":540,"passed_time":0.5283814673,"remaining_time":0.448294073},
{"learn":[3.890572728],"iteration":541,"passed_time":0.528852627,"remaining_time":0.4468902273},
{"learn":[3.885830213],"iteration":542,"passed_time":0.5294837017,"remaining_time":0.4456244046},
{"learn":[3.881000314],"iteration":543,"passed_time":0.5301001096,"remaining_time":0.4443486212},
{"learn":[3.878832458],"iteration":544,"passed_time":0.5308708914,"remaining_time":0.4432041387},
{"learn":[3.874324501],"iteration":545,"passed_time":0.531654506,"remaining_time":0.4420716955},
{"learn":[3.872446379],"iteration":546,"passed_time":0.5324239958,"remaining_time":0.4409288302},
{"learn":[3.870585035],"iteration":547,"passed_time":0.5331856518,"remaining_time":0.439780866},
{"learn":[3.866277061],"iteration":548,"passed_time":0.5338721847,"remaining_time":0.4385725962},
{"learn":[3.862730431],"iteration":549,"passed_time":0.5346290917,"remaining_time":0.4374238023},
{"learn":[3.860073949],"iteration":550,"passed_time":0.535284208,"remaining_time":0.4361934835},
{"learn":[3.858342068],"iteration":551,"passed_time":0.5365476073,"remaining_time":0.4354589277},
{"learn":[3.857791088],"iteration":552,"passed_time":0.5371473904,"remaining_time":0.4341860461},
{"learn":[3.854518848],"iteration":553,"passed_time":0.5377551733,"remaining_time":0.4329220348},
{"learn":[3.852265755],"iteration":554,"passed_time":0.5383717902,"remaining_time":0.4316674714},
{"learn":[3.848907558],"iteration":555,"passed_time":0.5390229906,"remaining_time":0.4304428198},
{"learn":[3.845146023],"iteration":556,"passed_time":0.5396401904,"remaining_time":0.4291931855},
{"learn":[3.844889413],"iteration":557,"passed_time":0.5402241827,"remaining_time":0.4279195139},
{"learn":[3.844726571],"iteration":558,"passed_time":0.5408451325,"remaining_time":0.4266774659},
{"learn":[3.841900916],"iteration":559,"passed_time":0.5414650403,"remaining_time":0.4254368174},
{"learn":[3.840383718],"iteration":560,"passed_time":0.5420551165,"remaining_time":0.4241750377},
{"learn":[3.839139543],"iteration":561,"passed_time":0.5426821082,"remaining_time":0.4229444188},
{"learn":[3.836328404],"iteration":562,"passed_time":0.5433278906,"remaining_time":0.4217305297},
{"learn":[3.834206881],"iteration":563,"passed_time":0.5440822137,"remaining_time":0.4206025623},
{"learn":[3.832525839],"iteration":564,"passed_time":0.5448243709,"remaining_time":0.419466551},
{"learn":[3.830607452],"iteration":565,"passed_time":0.54564336,"remaining_time":0.418390845},
{"learn":[3.829262782],"iteration":566,"passed_time":0.5465149325,"remaining_time":0.4173562007},
{"learn":[3.827529276],"iteration":567,"passed_time":0.547307589,"remaining_time":0.41626211},
{"learn":[3.82512405],"iteration":568,"passed_time":0.5479477466,"remaining_time":0.4150535655},
{"learn":[3.823865425],"iteration":569,"passed_time":0.5487498609,"remaining_time":0.4139691933},
{"learn":[3.820752341],"iteration":570,"passed_time":0.5494406438,"remaining_time":0.412802165},
{"learn":[3.818666233],"iteration":571,"passed_time":0.5500645516,"remaining_time":0.4115867624},
{"learn":[3.815680181],"iteration":572,"passed_time":0.5507467505,"remaining_time":0.410416863},
{"learn":[3.813240938],"iteration":573,"passed_time":0.5513518265,"remaining_time":0.4091914253},
{"learn":[3.812367821],"iteration":574,"passed_time":0.5520026929,"remaining_time":0.4080019904},
{"learn":[3.809256299],"iteration":575,"passed_time":0.5527835996,"remaining_time":0.4069101497},
{"learn":[3.808113875],"iteration":576,"passed_time":0.5534646316,"remaining_time":0.4057461684},
{"learn":[3.807885799],"iteration":577,"passed_time":0.5542245386,"remaining_time":0.4046414451},
{"learn":[3.807699706],"iteration":578,"passed_time":0.5548544892,"remaining_time":0.4034434196},
{"learn":[3.805666208],"iteration":579,"passed_time":0.555479689,"remaining_time":0.4022439127},
{"learn":[3.803331411],"iteration":580,"passed_time":0.5561210555,"remaining_time":0.4010580417},
{"learn":[3.798827747],"iteration":581,"passed_time":0.5567464222,"remaining_time":0.3998625507},
{"learn":[3.795912582],"iteration":582,"passed_time":0.5573319565,"remaining_time":0.3986405246},
{"learn":[3.793675263],"iteration":583,"passed_time":0.5579970727,"remaining_time":0.3974773668},
{"learn":[3.792711572],"iteration":584,"passed_time":0.5586272303,"remaining_time":0.3962911121},
{"learn":[3.788863471],"iteration":585,"passed_time":0.5592479721,"remaining_time":0.3951001032},
{"learn":[3.787058285],"iteration":586,"passed_time":0.5602750006,"remaining_time":0.3941968914},
{"learn":[3.78604757],"iteration":587,"passed_time":0.5615515247,"remaining_time":0.3934680751},
{"learn":[3.784159822],"iteration":588,"passed_time":0.5624410959,"remaining_time":0.3924673861},
{"learn":[3.782781541],"iteration":589,"passed_time":0.5632493772,"remaining_time":0.3914105842},
{"learn":[3.780353734],"iteration":590,"passed_time":0.5640425747,"remaining_time":0.3903441845},
{"learn":[3.777927915],"iteration":591,"passed_time":0.5647108159,"remaining_time":0.3891925893},
{"learn":[3.774241755],"iteration":592,"passed_time":0.5655221802,"remaining_time":0.3881408555},
{"learn":[3.770607861],"iteration":593,"passed_time":0.5663101278,"remaining_time":0.3870739257},
{"learn":[3.767094151],"iteration":594,"passed_time":0.5671664914,"remaining_time":0.3860545026},
{"learn":[3.765483417],"iteration":595,"passed_time":0.5683790584,"remaining_time":0.3852770799},
{"learn":[3.764204757],"iteration":596,"passed_time":0.5692245892,"remaining_time":0.3842504346},
{"learn":[3.763950411],"iteration":597,"passed_time":0.5703256997,"remaining_time":0.3833962061},
{"learn":[3.762551494],"iteration":598,"passed_time":0.5713686859,"remaining_time":0.3825022421},
{"learn":[3.759989574],"iteration":599,"passed_time":0.5724114641,"remaining_time":0.3816076427},
{"learn":[3.756627667],"iteration":600,"passed_time":0.5732181614,"remaining_time":0.3805558176},
{"learn":[3.754864207],"iteration":601,"passed_time":0.5740473584,"remaining_time":0.3795196822},
{"learn":[3.75302647],"iteration":602,"passed_time":0.5747044328,"remaining_time":0.3783709118},
{"learn":[3.750575553],"iteration":603,"passed_time":0.5754988382,"remaining_time":0.3773138079},
{"learn":[3.748180897],"iteration":604,"passed_time":0.5763003697,"remaining_time":0.3762622248},
{"learn":[3.744948199],"iteration":605,"passed_time":0.5771120259,"remaining_time":0.3752180499},
{"learn":[3.743045585],"iteration":606,"passed_time":0.5778698079,"remaining_time":0.3741397603},
{"learn":[3.741378519],"iteration":607,"passed_time":0.5785795075,"remaining_time":0.3730315246},
{"learn":[3.739818063],"iteration":608,"passed_time":0.5792778733,"remaining_time":0.3719173209},
{"learn":[3.739686368],"iteration":609,"passed_time":0.5800299043,"remaining_time":0.3708387913},
{"learn":[3.738017565],"iteration":610,"passed_time":0.5807603537,"remaining_time":0.3697475901},
{"learn":[3.737184734],"iteration":611,"passed_time":0.5815492602,"remaining_time":0.368694629},
{"learn":[3.73468758],"iteration":612,"passed_time":0.5823483327,"remaining_time":0.3676489474},
{"learn":[3.733099764],"iteration":613,"passed_time":0.583383194,"remaining_time":0.3667523011},
{"learn":[3.728959574],"iteration":614,"passed_time":0.5842660993,"remaining_time":0.3657600784},
{"learn":[3.72737107],"iteration":615,"passed_time":0.5850688387,"remaining_time":0.3647182371},
{"learn":[3.725358023],"iteration":616,"passed_time":0.5858542033,"remaining_time":0.3636663855},
{"learn":[3.724969629],"iteration":617,"passed_time":0.5867427746,"remaining_time":0.3626791908},
{"learn":[3.722534752],"iteration":618,"passed_time":0.5875647637,"remaining_time":0.3616513327},
{"learn":[3.719562679],"iteration":619,"passed_time":0.5883398365,"remaining_time":0.3605953836},
{"learn":[3.718485585],"iteration":620,"passed_time":0.5891232011,"remaining_time":0.3595453997},
{"learn":[3.715967452],"iteration":621,"passed_time":0.5898927329,"remaining_time":0.3584878666},
{"learn":[3.713573245],"iteration":622,"passed_time":0.5907052642,"remaining_time":0.3574572786},
{"learn":[3.710336959],"iteration":623,"passed_time":0.591624918,"remaining_time":0.3564919378},
{"learn":[3.707026766],"iteration":624,"passed_time":0.5925416139,"remaining_time":0.3555249683},
{"learn":[3.704331449],"iteration":625,"passed_time":0.5934090194,"remaining_time":0.3545287113},
{"learn":[3.700290614],"iteration":626,"passed_time":0.5946205874,"remaining_time":0.3537376062},
{"learn":[3.697980185],"iteration":627,"passed_time":0.5956842813,"remaining_time":0.3528575679},
{"learn":[3.69519489],"iteration":628,"passed_time":0.5966092271,"remaining_time":0.3518951085},
{"learn":[3.693864254],"iteration":629,"passed_time":0.5973367175,"remaining_time":0.3508168023},
{"learn":[3.69314254],"iteration":630,"passed_time":0.5980041677,"remaining_time":0.3497044974},
{"learn":[3.691140316],"iteration":631,"passed_time":0.5986804917,"remaining_time":0.3485987673},
{"learn":[3.688634407],"iteration":632,"passed_time":0.59934215,"remaining_time":0.3474858911},
{"learn":[3.688143798],"iteration":633,"passed_time":0.6000298909,"remaining_time":0.3463894954},
{"learn":[3.687771681],"iteration":634,"passed_time":0.6007583392,"remaining_time":0.3453177856},
{"learn":[3.686447046],"iteration":635,"passed_time":0.6018679916,"remaining_time":0.3444653285},
{"learn":[3.682885529],"iteration":636,"passed_time":0.6024813585,"remaining_time":0.3433292514},
{"learn":[3.680956982],"iteration":637,"passed_time":0.6030937254,"remaining_time":0.3421942454},
{"learn":[3.678999641],"iteration":638,"passed_time":0.6037333419,"remaining_time":0.3410762698},
{"learn":[3.676514727],"iteration":639,"passed_time":0.6044309577,"remaining_time":0.3399924137},
{"learn":[3.673507885],"iteration":640,"passed_time":0.6051931556,"remaining_time":0.3389459327},
{"learn":[3.67247319],"iteration":641,"passed_time":0.6058746056,"remaining_time":0.3378553097},
{"learn":[3.670025115],"iteration":642,"passed_time":0.6067707187,"remaining_time":0.3368851424},
{"learn":[3.669694605],"iteration":643,"passed_time":0.6075631663,"remaining_time":0.3358578994},
{"learn":[3.667954279],"iteration":644,"passed_time":0.6088181497,"remaining_time":0.3350859583},
{"learn":[3.664979488],"iteration":645,"passed_time":0.6099588436,"remaining_time":0.3342498926},
{"learn":[3.663206461],"iteration":646,"passed_time":0.6110256635,"remaining_time":0.3333725799},
{"learn":[3.662007135],"iteration":647,"passed_time":0.6120841075,"remaining_time":0.3324901325},
{"learn":[3.658199194],"iteration":648,"passed_time":0.6130052203,"remaining_time":0.3315328695},
{"learn":[3.656591414],"iteration":649,"passed_time":0.6139034164,"remaining_time":0.3305633781},
{"learn":[3.656500198],"iteration":650,"passed_time":0.6145634917,"remaining_time":0.3294664495},
{"learn":[3.655582168],"iteration":651,"passed_time":0.6152811912,"remaining_time":0.3284016174},
{"learn":[3.655223271],"iteration":652,"passed_time":0.6161095143,"remaining_time":0.3273966332},
{"learn":[3.653793239],"iteration":653,"passed_time":0.616884462,"remaining_time":0.3263639509},
{"learn":[3.653221846],"iteration":654,"passed_time":0.6175418703,"remaining_time":0.3252701454},
{"learn":[3.651811313],"iteration":655,"passed_time":0.6183076102,"remaining_time":0.3242344785},
{"learn":[3.649986354],"iteration":656,"passed_time":0.6189685595,"remaining_time":0.3231449253},
{"learn":[3.647932594],"iteration":657,"passed_time":0.6195851343,"remaining_time":0.3220336108},
{"learn":[3.644332926],"iteration":658,"passed_time":0.6202382087,"remaining_time":0.3209426846},
{"learn":[3.643068891],"iteration":659,"passed_time":0.620891867,"remaining_time":0.319853386},
{"learn":[3.641335374],"iteration":660,"passed_time":0.6215889408,"remaining_time":0.3187876716},
{"learn":[3.639792995],"iteration":661,"passed_time":0.6222995984,"remaining_time":0.3177300064},
{"learn":[3.63701354],"iteration":662,"passed_time":0.6231037958,"remaining_time":0.3167209339},
{"learn":[3.635973895],"iteration":663,"passed_time":0.6238842855,"remaining_time":0.3157004818},
{"learn":[3.634796408],"iteration":664,"passed_time":0.6248009403,"remaining_time":0.3147493459},
{"learn":[3.633052748],"iteration":665,"passed_time":0.6255408476,"remaining_time":0.3137096743},
{"learn":[3.629747856],"iteration":666,"passed_time":0.6262269635,"remaining_time":0.3126440462},
{"learn":[3.628111041],"iteration":667,"passed_time":0.6269233293,"remaining_time":0.3115846487},
{"learn":[3.62786774],"iteration":668,"passed_time":0.6275685707,"remaining_time":0.3105010417},
{"learn":[3.626708964],"iteration":669,"passed_time":0.6282609366,"remaining_time":0.3094419538},
{"learn":[3.622924473],"iteration":670,"passed_time":0.6290787178,"remaining_time":0.3084454518},
{"learn":[3.622760423],"iteration":671,"passed_time":0.6299482473,"remaining_time":0.3074747397},
{"learn":[3.622242532],"iteration":672,"passed_time":0.6309876925,"remaining_time":0.3065868878},
{"learn":[3.620613214],"iteration":673,"passed_time":0.6317792661,"remaining_time":0.3055786955},
{"learn":[3.618983878],"iteration":674,"passed_time":0.6324582571,"remaining_time":0.3045169386},
{"learn":[3.617608895],"iteration":675,"passed_time":0.6330281245,"remaining_time":0.3034040124},
{"learn":[3.615093381],"iteration":676,"passed_time":0.6336616162,"remaining_time":0.3023230458},
{"learn":[3.615014704],"iteration":677,"passed_time":0.6342181088,"remaining_time":0.3012068304},
{"learn":[3.612893523],"iteration":678,"passed_time":0.6348377256,"remaining_time":0.3001221059},
{"learn":[3.611548969],"iteration":679,"passed_time":0.6354699253,"remaining_time":0.2990446707},
{"learn":[3.607562829],"iteration":680,"passed_time":0.6361161257,"remaining_time":0.2979751015},
{"learn":[3.607378072],"iteration":681,"passed_time":0.636699201,"remaining_time":0.2968773401},
{"learn":[3.602659333],"iteration":682,"passed_time":0.6374755237,"remaining_time":0.2958707775},
{"learn":[3.600320934],"iteration":683,"passed_time":0.6386246335,"remaining_time":0.2950371114},
{"learn":[3.600157167],"iteration":684,"passed_time":0.6393238743,"remaining_time":0.2939956502},
{"learn":[3.59776412],"iteration":685,"passed_time":0.6401265297,"remaining_time":0.2930025223},
{"learn":[3.595609292],"iteration":686,"passed_time":0.6411279334,"remaining_time":0.2921004995},
{"learn":[3.593615537],"iteration":687,"passed_time":0.6421722116,"remaining_time":0.2912176309},
{"learn":[3.593310012],"iteration":688,"passed_time":0.6430909495,"remaining_time":0.2902776274},
{"learn":[3.591161675],"iteration":689,"passed_time":0.6439384803,"remaining_time":0.289305694},
{"learn":[3.587787916],"iteration":690,"passed_time":0.6450072571,"remaining_time":0.2884330571},
{"learn":[3.58615798],"iteration":691,"passed_time":0.6460291596,"remaining_time":0.2875389901},
{"learn":[3.585332246],"iteration":692,"passed_time":0.6469736891,"remaining_time":0.2866102779},
{"learn":[3.584824536],"iteration":693,"passed_time":0.6478084281,"remaining_time":0.285633111},
{"learn":[3.580712521],"iteration":694,"passed_time":0.6486933334,"remaining_time":0.2846783693},
{"learn":[3.579123945],"iteration":695,"passed_time":0.6494865309,"remaining_time":0.2836837721},
{"learn":[3.57769234],"iteration":696,"passed_time":0.6503628943,"remaining_time":0.2827259067},
{"learn":[3.575198055],"iteration":697,"passed_time":0.6513269656,"remaining_time":0.2818062229},
{"learn":[3.574950409],"iteration":698,"passed_time":0.6524919092,"remaining_time":0.2809729108},
{"learn":[3.573856039],"iteration":699,"passed_time":0.6535071458,"remaining_time":0.280074491},
{"learn":[3.570748685],"iteration":700,"passed_time":0.6544675081,"remaining_time":0.2791523323},
{"learn":[3.567386718],"iteration":701,"passed_time":0.6555859513,"remaining_time":0.2782971702},
{"learn":[3.566399859],"iteration":702,"passed_time":0.6567131864,"remaining_time":0.2774449735},
{"learn":[3.565306841],"iteration":703,"passed_time":0.658406955,"remaining_time":0.276830197},
{"learn":[3.562192111],"iteration":704,"passed_time":0.6597734789,"remaining_time":0.2760754273},
{"learn":[3.561556048],"iteration":705,"passed_time":0.6607074665,"remaining_time":0.2751388033},
{"learn":[3.559911841],"iteration":706,"passed_time":0.6617947442,"remaining_time":0.2742657143},
{"learn":[3.559189111],"iteration":707,"passed_time":0.6629319381,"remaining_time":0.2734126073},
{"learn":[3.555259326],"iteration":708,"passed_time":0.6640464654,"remaining_time":0.2725493955},
{"learn":[3.553052809],"iteration":709,"passed_time":0.6692819802,"remaining_time":0.2733686961},
{"learn":[3.550035773],"iteration":710,"passed_time":0.6702415515,"remaining_time":0.2724329232},
{"learn":[3.549798944],"iteration":711,"passed_time":0.6748266988,"remaining_time":0.2729636085},
{"learn":[3.548076438],"iteration":712,"passed_time":0.6757128541,"remaining_time":0.2719910086},
{"learn":[3.546244499],"iteration":713,"passed_time":0.6765805927,"remaining_time":0.2710112738},
{"learn":[3.543936225],"iteration":714,"passed_time":0.6774733719,"remaining_time":0.2700418335},
{"learn":[3.540928451],"iteration":715,"passed_time":0.6782750273,"remaining_time":0.2690364633},
{"learn":[3.537077221],"iteration":716,"passed_time":0.6792875969,"remaining_time":0.2681149092},
{"learn":[3.533421066],"iteration":717,"passed_time":0.6803497488,"remaining_time":0.2672125754},
{"learn":[3.53327343],"iteration":718,"passed_time":0.6814151927,"remaining_time":0.2663110837},
{"learn":[3.532176856],"iteration":719,"passed_time":0.6824183045,"remaining_time":0.2653848962},
{"learn":[3.530591302],"iteration":720,"passed_time":0.683515248,"remaining_time":0.2644948047},
{"learn":[3.530482066],"iteration":721,"passed_time":0.6846618998,"remaining_time":0.26362328},
{"learn":[3.528541017],"iteration":722,"passed_time":0.6857123859,"remaining_time":0.2627141506},
{"learn":[3.527357825],"iteration":723,"passed_time":0.6866475825,"remaining_time":0.2617606806},
{"learn":[3.523138956],"iteration":724,"passed_time":0.6874719886,"remaining_time":0.2607652371},
{"learn":[3.521123421],"iteration":725,"passed_time":0.6883799346,"remaining_time":0.2598017935},
{"learn":[3.520888189],"iteration":726,"passed_time":0.6894250038,"remaining_time":0.2588899946},
{"learn":[3.517281201],"iteration":727,"passed_time":0.6905722386,"remaining_time":0.2580160013},
{"learn":[3.514617921],"iteration":728,"passed_time":0.6916429325,"remaining_time":0.2571128048},
{"learn":[3.511373498],"iteration":729,"passed_time":0.6926927516,"remaining_time":0.2562014287},
{"learn":[3.508827416],"iteration":730,"passed_time":0.6940116512,"remaining_time":0.2553886924},
{"learn":[3.508499236],"iteration":731,"passed_time":0.6948849316,"remaining_time":0.2544114231},
{"learn":[3.505761627],"iteration":732,"passed_time":0.6961185823,"remaining_time":0.2535657046},
{"learn":[3.501707163],"iteration":733,"passed_time":0.6972880248,"remaining_time":0.2526956602},
{"learn":[3.50073721],"iteration":734,"passed_time":0.7028952007,"remaining_time":0.2534248003},
{"learn":[3.497102505],"iteration":735,"passed_time":0.7037163148,"remaining_time":0.2524199825},
{"learn":[3.496216756],"iteration":736,"passed_time":0.704760259,"remaining_time":0.2514951806},
{"learn":[3.493142386],"iteration":737,"passed_time":0.7059026599,"remaining_time":0.2506050094},
{"learn":[3.492548983],"iteration":738,"passed_time":0.7066987744,"remaining_time":0.249591854},
{"learn":[3.491421661],"iteration":739,"passed_time":0.7075330554,"remaining_time":0.2485926951},
{"learn":[3.490777283],"iteration":740,"passed_time":0.709074868,"remaining_time":0.2478412831},
{"learn":[3.489203536],"iteration":741,"passed_time":0.7115199187,"remaining_time":0.2474018046},
{"learn":[3.488638287],"iteration":742,"passed_time":0.7126549877,"remaining_time":0.2465038113},
{"learn":[3.487061147],"iteration":743,"passed_time":0.7137793898,"remaining_time":0.2456015105},
{"learn":[3.483951015],"iteration":744,"passed_time":0.7149636661,"remaining_time":0.2447191072},
{"learn":[3.483499848],"iteration":745,"passed_time":0.7161017341,"remaining_time":0.2438201615},
{"learn":[3.482302079],"iteration":746,"passed_time":0.7172954263,"remaining_time":0.2429394148},
{"learn":[3.481901953],"iteration":747,"passed_time":0.7181426241,"remaining_time":0.241941098},
{"learn":[3.481055915],"iteration":748,"passed_time":0.7189594463,"remaining_time":0.2409330054},
{"learn":[3.479977848],"iteration":749,"passed_time":0.7197433109,"remaining_time":0.239914437},
{"learn":[3.477717446],"iteration":750,"passed_time":0.7205190917,"remaining_time":0.2388938133},
{"learn":[3.476384979],"iteration":751,"passed_time":0.7213080392,"remaining_time":0.2378781832},
{"learn":[3.47505308],"iteration":752,"passed_time":0.722083612,"remaining_time":0.2368587678},
{"learn":[3.472451605],"iteration":753,"passed_time":0.7228973092,"remaining_time":0.2358524378},
{"learn":[3.47160405],"iteration":754,"passed_time":0.7238007143,"remaining_time":0.2348757285},
{"learn":[3.46952203],"iteration":755,"passed_time":0.7248465754,"remaining_time":0.233945191},
{"learn":[3.468514822],"iteration":756,"passed_time":0.7260501015,"remaining_time":0.2330649599},
{"learn":[3.466991367],"iteration":757,"passed_time":0.7276587883,"remaining_time":0.2323132279},
{"learn":[3.46311613],"iteration":758,"passed_time":0.7302441291,"remaining_time":0.231869348},
{"learn":[3.461405616],"iteration":759,"passed_time":0.7309828693,"remaining_time":0.2308366956},
{"learn":[3.460163092],"iteration":760,"passed_time":0.7318498578,"remaining_time":0.2298450933},
{"learn":[3.458895566],"iteration":761,"passed_time":0.7326055148,"remaining_time":0.2288190453},
{"learn":[3.456591852],"iteration":762,"passed_time":0.7332479234,"remaining_time":0.2277585293},
{"learn":[3.455587468],"iteration":763,"passed_time":0.7339168315,"remaining_time":0.2267072935},
{"learn":[3.454131537],"iteration":764,"passed_time":0.7345189065,"remaining_time":0.2256365268},
{"learn":[3.451299249],"iteration":765,"passed_time":0.7352293132,"remaining_time":0.2246000774},
{"learn":[3.449579715],"iteration":766,"passed_time":0.7360275946,"remaining_time":0.2235911728},
{"learn":[3.447358121],"iteration":767,"passed_time":0.7367414602,"remaining_time":0.2225573161},
{"learn":[3.445767784],"iteration":768,"passed_time":0.7376041578,"remaining_time":0.2215689993},
{"learn":[3.444509121],"iteration":769,"passed_time":0.7383824385,"remaining_time":0.2205557933},
{"learn":[3.442760386],"iteration":770,"passed_time":0.7391945937,"remaining_time":0.2195532581},
{"learn":[3.441191917],"iteration":771,"passed_time":0.7400497074,"remaining_time":0.2185639032},
{"learn":[3.439513273],"iteration":772,"passed_time":0.7407342824,"remaining_time":0.2175248151},
{"learn":[3.436394263],"iteration":773,"passed_time":0.7413710239,"remaining_time":0.2164726762},
{"learn":[3.433912023],"iteration":774,"passed_time":0.7424325099,"remaining_time":0.2155449222},
{"learn":[3.431033404],"iteration":775,"passed_time":0.7441069048,"remaining_time":0.2147937457},
{"learn":[3.429748976],"iteration":776,"passed_time":0.7449338938,"remaining_time":0.2137969863},
{"learn":[3.428484841],"iteration":777,"passed_time":0.7456860089,"remaining_time":0.2127792982},
{"learn":[3.427620792],"iteration":778,"passed_time":0.746512998,"remaining_time":0.2117835334},
{"learn":[3.424522054],"iteration":779,"passed_time":0.7474227359,"remaining_time":0.2108115409},
{"learn":[3.423295349],"iteration":780,"passed_time":0.748553013,"remaining_time":0.2099015491},
{"learn":[3.420901882],"iteration":781,"passed_time":0.7494511261,"remaining_time":0.208926273},
{"learn":[3.419588633],"iteration":782,"passed_time":0.7503788638,"remaining_time":0.2079594042},
{"learn":[3.418721017],"iteration":783,"passed_time":0.7511506866,"remaining_time":0.206949679},
{"learn":[3.415843818],"iteration":784,"passed_time":0.7519455101,"remaining_time":0.2059468595},
{"learn":[3.41475122],"iteration":785,"passed_time":0.7526869583,"remaining_time":0.204930037},
{"learn":[3.414423873],"iteration":786,"passed_time":0.7533698663,"remaining_time":0.2038980705},
{"learn":[3.413633542],"iteration":787,"passed_time":0.7541752716,"remaining_time":0.2028999462},
{"learn":[3.412305986],"iteration":788,"passed_time":0.7553119646,"remaining_time":0.2019909056},
{"learn":[3.411294721],"iteration":789,"passed_time":0.7565961146,"remaining_time":0.2011204862},
{"learn":[3.410125732],"iteration":790,"passed_time":0.7576529756,"remaining_time":0.2001889658},
{"learn":[3.407957555],"iteration":791,"passed_time":0.7588946262,"remaining_time":0.1993056594},
{"learn":[3.407312241],"iteration":792,"passed_time":0.7597924484,"remaining_time":0.1983316984},
{"learn":[3.405222567],"iteration":793,"passed_time":0.7605853129,"remaining_time":0.1973306983},
{"learn":[3.403995717],"iteration":794,"passed_time":0.7613992181,"remaining_time":0.1963356474},
{"learn":[3.403383485],"iteration":795,"passed_time":0.762392039,"remaining_time":0.1953869045},
{"learn":[3.400712639],"iteration":796,"passed_time":0.7632634855,"remaining_time":0.1944071362},
{"learn":[3.399801664],"iteration":797,"passed_time":0.763981268,"remaining_time":0.193388742},
{"learn":[3.395944803],"iteration":798,"passed_time":0.7646650089,"remaining_time":0.1923625367},
{"learn":[3.393884216],"iteration":799,"passed_time":0.7653860824,"remaining_time":0.1913465206},
{"learn":[3.392911985],"iteration":800,"passed_time":0.7660674484,"remaining_time":0.1903213761},
{"learn":[3.391103219],"iteration":801,"passed_time":0.7668228544,"remaining_time":0.189315368},
{"learn":[3.390830677],"iteration":802,"passed_time":0.7674530541,"remaining_time":0.1882792673},
{"learn":[3.388941468],"iteration":803,"passed_time":0.7681236292,"remaining_time":0.1872540191},
{"learn":[3.387348605],"iteration":804,"passed_time":0.7687812875,"remaining_time":0.1862265231},
{"learn":[3.386424114],"iteration":805,"passed_time":0.7694958611,"remaining_time":0.185213644},
{"learn":[3.383700774],"iteration":806,"passed_time":0.7703154332,"remaining_time":0.1842266154},
{"learn":[3.383100156],"iteration":807,"passed_time":0.771013424,"remaining_time":0.1832111106},
{"learn":[3.382762454],"iteration":808,"passed_time":0.7716627074,"remaining_time":0.1821848914},
{"learn":[3.380717052],"iteration":809,"passed_time":0.772521613,"remaining_time":0.1812087734},
{"learn":[3.37763715],"iteration":810,"passed_time":0.7734498088,"remaining_time":0.1802490923},
{"learn":[3.374198156],"iteration":811,"passed_time":0.7742463402,"remaining_time":0.1792590049},
{"learn":[3.372913193],"iteration":812,"passed_time":0.7749132064,"remaining_time":0.178239569},
{"learn":[3.369035989],"iteration":813,"passed_time":0.7755021146,"remaining_time":0.1772031859},
{"learn":[3.367867605],"iteration":814,"passed_time":0.7763141869,"remaining_time":0.1762185578},
{"learn":[3.36391456],"iteration":815,"passed_time":0.7771662166,"remaining_time":0.1752433626},
{"learn":[3.361951345],"iteration":816,"passed_time":0.7780215383,"remaining_time":0.1742692063},
{"learn":[3.361032484],"iteration":817,"passed_time":0.7787625705,"remaining_time":0.1732699118},
{"learn":[3.359848384],"iteration":818,"passed_time":0.7796108503,"remaining_time":0.1722949498},
{"learn":[3.35908872],"iteration":819,"passed_time":0.7804532982,"remaining_time":0.1713190167},
{"learn":[3.358175476],"iteration":820,"passed_time":0.7816084079,"remaining_time":0.1704115774},
{"learn":[3.357538387],"iteration":821,"passed_time":0.7828987658,"remaining_time":0.1695328228},
{"learn":[3.35576498],"iteration":822,"passed_time":0.789764509,"remaining_time":0.1698521484},
{"learn":[3.353547141],"iteration":823,"passed_time":0.7910165765,"remaining_time":0.1689549969},
{"learn":[3.351924115],"iteration":824,"passed_time":0.7918282328,"remaining_time":0.1679635645},
{"learn":[3.351687617],"iteration":825,"passed_time":0.7927524295,"remaining_time":0.1669962745},
{"learn":[3.350161015],"iteration":826,"passed_time":0.793549377,"remaining_time":0.1660024694},
{"learn":[3.349035602],"iteration":827,"passed_time":0.7943544073,"remaining_time":0.1650108189},
{"learn":[3.347975029],"iteration":828,"passed_time":0.7952308128,"remaining_time":0.1640343414},
{"learn":[3.346972473],"iteration":829,"passed_time":0.7961603835,"remaining_time":0.1630689942},
{"learn":[3.345008059],"iteration":830,"passed_time":0.797256202,"remaining_time":0.1621375429},
{"learn":[3.343882438],"iteration":831,"passed_time":0.7983492285,"remaining_time":0.1612051327},
{"learn":[3.343129153],"iteration":832,"passed_time":0.7994616728,"remaining_time":0.1602762297},
{"learn":[3.339826073],"iteration":833,"passed_time":0.8033105389,"remaining_time":0.1598915461},
{"learn":[3.337466957],"iteration":834,"passed_time":0.8049739749,"remaining_time":0.1590667136},
{"learn":[3.335400157],"iteration":835,"passed_time":0.8059264203,"remaining_time":0.1581003982},
{"learn":[3.332782358],"iteration":836,"passed_time":0.8073331097,"remaining_time":0.1572225769},
{"learn":[3.332693343],"iteration":837,"passed_time":0.80822314,"remaining_time":0.1562436142},
{"learn":[3.330759243],"iteration":838,"passed_time":0.8092200858,"remaining_time":0.15528538},
{"learn":[3.329570291],"iteration":839,"passed_time":0.8100159083,"remaining_time":0.1542887444},
{"learn":[3.329478807],"iteration":840,"passed_time":0.8108952716,"remaining_time":0.1533083807},
{"learn":[3.328960554],"iteration":841,"passed_time":0.8118339682,"remaining_time":0.1523393907},
{"learn":[3.326161482],"iteration":842,"passed_time":0.8126542914,"remaining_time":0.1513484267},
{"learn":[3.325324321],"iteration":843,"passed_time":0.8134557808,"remaining_time":0.150354386},
{"learn":[3.324044875],"iteration":844,"passed_time":0.8142620611,"remaining_time":0.1493616798},
{"learn":[3.322493291],"iteration":845,"passed_time":0.8151080499,"remaining_time":0.1483766427},
{"learn":[3.32133187],"iteration":846,"passed_time":0.8159098303,"remaining_time":0.1473839481},
{"learn":[3.318574012],"iteration":847,"passed_time":0.8167179026,"remaining_time":0.1463928316},
{"learn":[3.318439903],"iteration":848,"passed_time":0.817973928,"remaining_time":0.1454818176},
{"learn":[3.317503145],"iteration":849,"passed_time":0.8199346101,"remaining_time":0.144694343},
{"learn":[3.316078001],"iteration":850,"passed_time":0.8209948461,"remaining_time":0.1437464537},
{"learn":[3.315255447],"iteration":851,"passed_time":0.821830752,"remaining_time":0.1427593325},
{"learn":[3.314073936],"iteration":852,"passed_time":0.8226515332,"remaining_time":0.1417699594},
{"learn":[3.312790304],"iteration":853,"passed_time":0.82349998,"remaining_time":0.1407857109},
{"learn":[3.311519553],"iteration":854,"passed_time":0.8242832616,"remaining_time":0.1397907286},
{"learn":[3.309746405],"iteration":855,"passed_time":0.8251383343,"remaining_time":0.1388083179},
{"learn":[3.308943311],"iteration":856,"passed_time":0.8261346961,"remaining_time":0.1378497801},
{"learn":[3.308581505],"iteration":857,"passed_time":0.8271863492,"remaining_time":0.1369003049},
{"learn":[3.307689017],"iteration":858,"passed_time":0.8280566297,"remaining_time":0.1359208205},
{"learn":[3.306982868],"iteration":859,"passed_time":0.828942785,"remaining_time":0.1349441743},
{"learn":[3.305426406],"iteration":860,"passed_time":0.8297260666,"remaining_time":0.1339511304},
{"learn":[3.302678386],"iteration":861,"passed_time":0.8304946815,"remaining_time":0.1329562251},
{"learn":[3.300057769],"iteration":862,"passed_time":0.8315523755,"remaining_time":0.1320077352},
{"learn":[3.29985418],"iteration":863,"passed_time":0.832948065,"remaining_time":0.1311121954},
{"learn":[3.299123503],"iteration":864,"passed_time":0.8341068837,"remaining_time":0.130178531},
{"learn":[3.297668],"iteration":865,"passed_time":0.8353220336,"remaining_time":0.1292530629},
{"learn":[3.29697776],"iteration":866,"passed_time":0.8361503977,"remaining_time":0.1282675927},
{"learn":[3.295877359],"iteration":867,"passed_time":0.8368386796,"remaining_time":0.1272611817},
{"learn":[3.295310884],"iteration":868,"passed_time":0.8375425033,"remaining_time":0.1262578457},
{"learn":[3.293596194],"iteration":869,"passed_time":0.8383814502,"remaining_time":0.1252753891},
{"learn":[3.29198061],"iteration":870,"passed_time":0.8391643978,"remaining_time":0.1242849682},
{"learn":[3.291196364],"iteration":871,"passed_time":0.8399473875,"remaining_time":0.1232950294},
{"learn":[3.287473506],"iteration":872,"passed_time":0.8412129117,"remaining_time":0.1223757615},
{"learn":[3.285061875],"iteration":873,"passed_time":0.8419055276,"remaining_time":0.1213731081},
{"learn":[3.282051731],"iteration":874,"passed_time":0.8425656439,"remaining_time":0.1203665206},
{"learn":[3.280415491],"iteration":875,"passed_time":0.8440169167,"remaining_time":0.1194727142},
{"learn":[3.277492478],"iteration":876,"passed_time":0.8446820749,"remaining_time":0.1184673834},
{"learn":[3.276264782],"iteration":877,"passed_time":0.845354316,"remaining_time":0.1174638116},
{"learn":[3.27378979],"iteration":878,"passed_time":0.8464278848,"remaining_time":0.116516239},
{"learn":[3.273616736],"iteration":879,"passed_time":0.8477090768,"remaining_time":0.1155966923},
{"learn":[3.270748103],"iteration":880,"passed_time":0.8486176488,"remaining_time":0.1146259934},
{"learn":[3.269852401],"iteration":881,"passed_time":0.8495173869,"remaining_time":0.1136542536},
{"learn":[3.268531354],"iteration":882,"passed_time":0.8505866648,"remaining_time":0.1127051413},
{"learn":[3.267632259],"iteration":883,"passed_time":0.8516027344,"remaining_time":0.1117487751},
{"learn":[3.26606569],"iteration":884,"passed_time":0.8524083077,"remaining_time":0.1107649213},
{"learn":[3.264373784],"iteration":885,"passed_time":0.8531875064,"remaining_time":0.1097780764},
{"learn":[3.261338226],"iteration":886,"passed_time":0.85397683,"remaining_time":0.1087929896},
{"learn":[3.259345989],"iteration":887,"passed_time":0.8547771114,"remaining_time":0.1078097258},
{"learn":[3.256423243],"iteration":888,"passed_time":0.8556322671,"remaining_time":0.1068337251},
{"learn":[3.25545981],"iteration":889,"passed_time":0.8567321695,"remaining_time":0.1058882457},
{"learn":[3.252431942],"iteration":890,"passed_time":0.8575982831,"remaining_time":0.1049138191},
{"learn":[3.251730404],"iteration":891,"passed_time":0.8585377287,"remaining_time":0.1039485142},
{"learn":[3.25021876],"iteration":892,"passed_time":0.859341718,"remaining_time":0.1029670368},
{"learn":[3.249382931],"iteration":893,"passed_time":0.8601392915,"remaining_time":0.1019851956},
{"learn":[3.246509173],"iteration":894,"passed_time":0.8609210721,"remaining_time":0.1010019135},
{"learn":[3.245450005],"iteration":895,"passed_time":0.8625277169,"remaining_time":0.1001148243},
{"learn":[3.244245077],"iteration":896,"passed_time":0.8637539927,"remaining_time":0.09918245401},
{"learn":[3.241907245],"iteration":897,"passed_time":0.8647356047,"remaining_time":0.09822163884},
{"learn":[3.240417767],"iteration":898,"passed_time":0.8659175061,"remaining_time":0.09728327933},
{"learn":[3.24021676],"iteration":899,"passed_time":0.866984325,"remaining_time":0.09633159166},
{"learn":[3.239190925],"iteration":900,"passed_time":0.8693882932,"remaining_time":0.09552657162},
{"learn":[3.235478302],"iteration":901,"passed_time":0.8702822404,"remaining_time":0.09455394629},
{"learn":[3.235013394],"iteration":902,"passed_time":0.8711348121,"remaining_time":0.09357705069},
{"learn":[3.23478373],"iteration":903,"passed_time":0.8735074057,"remaining_time":0.09276184839},
{"learn":[3.233758482],"iteration":904,"passed_time":0.8745347671,"remaining_time":0.09180199213},
{"learn":[3.231584062],"iteration":905,"passed_time":0.875601587,"remaining_time":0.09084608077},
{"learn":[3.229901733],"iteration":906,"passed_time":0.8769751099,"remaining_time":0.0899213729},
{"learn":[3.229559168],"iteration":907,"passed_time":0.8785416312,"remaining_time":0.08901523135},
{"learn":[3.228444348],"iteration":908,"passed_time":0.8795706175,"remaining_time":0.0880538242},
{"learn":[3.228363081],"iteration":909,"passed_time":0.8812689701,"remaining_time":0.08715846957},
{"learn":[3.227258985],"iteration":910,"passed_time":0.8819433782,"remaining_time":0.08616131796},
{"learn":[3.22447298],"iteration":911,"passed_time":0.8828974486,"remaining_time":0.08519185907},
{"learn":[3.2228944],"iteration":912,"passed_time":0.8847780067,"remaining_time":0.08431071915},
{"learn":[3.222717809],"iteration":913,"passed_time":0.8854409569,"remaining_time":0.08331282527},
{"learn":[3.218729329],"iteration":914,"passed_time":0.8861555725,"remaining_time":0.08232046302},
{"learn":[3.21866972],"iteration":915,"passed_time":0.8868174387,"remaining_time":0.08132386993},
{"learn":[3.216353959],"iteration":916,"passed_time":0.8874863049,"remaining_time":0.08032864046},
{"learn":[3.213526348],"iteration":917,"passed_time":0.8882519198,"remaining_time":0.07934276407},
{"learn":[3.213417385],"iteration":918,"passed_time":0.888913827,"remaining_time":0.07834822632},
{"learn":[3.212000089],"iteration":919,"passed_time":0.8904659315,"remaining_time":0.07743182013},
{"learn":[3.210768131],"iteration":920,"passed_time":0.8912762538,"remaining_time":0.07645040613},
{"learn":[3.208768789],"iteration":921,"passed_time":0.8923516555,"remaining_time":0.07549178865},
{"learn":[3.20826308],"iteration":922,"passed_time":0.8933111009,"remaining_time":0.0745232446},
{"learn":[3.207113605],"iteration":923,"passed_time":0.8941450898,"remaining_time":0.07354440133},
{"learn":[3.205618742],"iteration":924,"passed_time":0.894887913,"remaining_time":0.07255847943},
{"learn":[3.204430549],"iteration":925,"passed_time":0.8956750276,"remaining_time":0.07157662208},
{"learn":[3.203585677],"iteration":926,"passed_time":0.8964851829,"remaining_time":0.0705969993},
{"learn":[3.202552395],"iteration":927,"passed_time":0.8973520464,"remaining_time":0.06962214153},
{"learn":[3.20118595],"iteration":928,"passed_time":0.898443573,"remaining_time":0.06866468642},
{"learn":[3.196545018],"iteration":929,"passed_time":0.8991545636,"remaining_time":0.06767830049},
{"learn":[3.19304465],"iteration":930,"passed_time":0.8999791777,"remaining_time":0.06670092724},
{"learn":[3.19054875],"iteration":931,"passed_time":0.900711751,"remaining_time":0.06571716638},
{"learn":[3.190449844],"iteration":932,"passed_time":0.9013511175,"remaining_time":0.06472725067},
{"learn":[3.188825492],"iteration":933,"passed_time":0.9020673581,"remaining_time":0.06374351781},
{"learn":[3.186289003],"iteration":934,"passed_time":0.9027265164,"remaining_time":0.06275638884},
{"learn":[3.185139366],"iteration":935,"passed_time":0.9034420489,"remaining_time":0.06177381531},
{"learn":[3.185084166],"iteration":936,"passed_time":0.9040300001,"remaining_time":0.06078323373},
{"learn":[3.183991673],"iteration":937,"passed_time":0.9049385301,"remaining_time":0.05981470028},
{"learn":[3.181713541],"iteration":938,"passed_time":0.9083785686,"remaining_time":0.05901074833},
{"learn":[3.180151352],"iteration":939,"passed_time":0.9091867239,"remaining_time":0.05803319514},
{"learn":[3.178911532],"iteration":940,"passed_time":0.9100512955,"remaining_time":0.05705953925},
{"learn":[3.17798744],"iteration":941,"passed_time":0.9108099105,"remaining_time":0.05607959109},
{"learn":[3.177511704],"iteration":942,"passed_time":0.912206517,"remaining_time":0.055138676},
{"learn":[3.175777038],"iteration":943,"passed_time":0.9129264235,"remaining_time":0.05415665224},
{"learn":[3.173345037],"iteration":944,"passed_time":0.9137373298,"remaining_time":0.05318047951},
{"learn":[3.173252423],"iteration":945,"passed_time":0.9144426954,"remaining_time":0.05219863166},
{"learn":[3.171446048],"iteration":946,"passed_time":0.9152719345,"remaining_time":0.05122430045},
{"learn":[3.170845305],"iteration":947,"passed_time":0.9160382163,"remaining_time":0.05024682199},
{"learn":[3.168430318],"iteration":948,"passed_time":0.9168641224,"remaining_time":0.04927299288},
{"learn":[3.166967061],"iteration":949,"passed_time":0.9175851129,"remaining_time":0.04829395331},
{"learn":[3.166351426],"iteration":950,"passed_time":0.918333269,"remaining_time":0.04731685613},
{"learn":[3.164723594],"iteration":951,"passed_time":0.9191761748,"remaining_time":0.04634501722},
{"learn":[3.161594547],"iteration":952,"passed_time":0.9200617881,"remaining_time":0.04537555513},
{"learn":[3.160407817],"iteration":953,"passed_time":0.9211477738,"remaining_time":0.04441593039},
{"learn":[3.157801289],"iteration":954,"passed_time":0.9227572525,"remaining_time":0.04348070823},
{"learn":[3.157545557],"iteration":955,"passed_time":0.9235452001,"remaining_time":0.04250626444},
{"learn":[3.157255345],"iteration":956,"passed_time":0.9245842703,"remaining_time":0.04154349386},
{"learn":[3.154581325],"iteration":957,"passed_time":0.9253720929,"remaining_time":0.04056954896},
{"learn":[3.152813117],"iteration":958,"passed_time":0.9262106648,"remaining_time":0.0395981619},
{"learn":[3.152118913],"iteration":959,"passed_time":0.9270887372,"remaining_time":0.03862869738},
{"learn":[3.151175062],"iteration":960,"passed_time":0.9278576021,"remaining_time":0.03765499113},
{"learn":[3.148993085],"iteration":961,"passed_time":0.9286696323,"remaining_time":0.03668341583},
{"learn":[3.148494583],"iteration":962,"passed_time":0.929449122,"remaining_time":0.03571092161},
{"learn":[3.148175008],"iteration":963,"passed_time":0.9301714455,"remaining_time":0.03473669298},
{"learn":[3.148022976],"iteration":964,"passed_time":0.9309360603,"remaining_time":0.03376452032},
{"learn":[3.147922485],"iteration":965,"passed_time":0.9321303786,"remaining_time":0.03280790152},
{"learn":[3.145650013],"iteration":966,"passed_time":0.9327967447,"remaining_time":0.03183277412},
{"learn":[3.143388016],"iteration":967,"passed_time":0.9334641939,"remaining_time":0.03085832046},
{"learn":[3.142642046],"iteration":968,"passed_time":0.9341970592,"remaining_time":0.02988659323},
{"learn":[3.139992994],"iteration":969,"passed_time":0.9349405914,"remaining_time":0.02891568839},
{"learn":[3.138046166],"iteration":970,"passed_time":0.9359937025,"remaining_time":0.02795449781},
{"learn":[3.135602107],"iteration":971,"passed_time":0.9371196036,"remaining_time":0.02699521492},
{"learn":[3.135483699],"iteration":972,"passed_time":0.9379659254,"remaining_time":0.02602783143},
{"learn":[3.135030005],"iteration":973,"passed_time":0.9391621596,"remaining_time":0.02507003711},
{"learn":[3.134550115],"iteration":974,"passed_time":0.939958982,"remaining_time":0.02410151236},
{"learn":[3.132502083],"iteration":975,"passed_time":0.9407482216,"remaining_time":0.02313315299},
{"learn":[3.130796607],"iteration":976,"passed_time":0.9415995013,"remaining_time":0.02216662081},
{"learn":[3.130518388],"iteration":977,"passed_time":0.9424701978,"remaining_time":0.0212007611},
{"learn":[3.129565137],"iteration":978,"passed_time":0.9430977725,"remaining_time":0.02022988072},
{"learn":[3.125684779],"iteration":979,"passed_time":0.9437553058,"remaining_time":0.01926031236},
{"learn":[3.12407028],"iteration":980,"passed_time":0.9444140061,"remaining_time":0.01829140277},
{"learn":[3.121562592],"iteration":981,"passed_time":0.9450604136,"remaining_time":0.01732289964},
{"learn":[3.121132505],"iteration":982,"passed_time":0.9457161549,"remaining_time":0.01635521326},
{"learn":[3.118616439],"iteration":983,"passed_time":0.9463446056,"remaining_time":0.01538771716},
{"learn":[3.117479998],"iteration":984,"passed_time":0.9469876801,"remaining_time":0.01442113218},
{"learn":[3.116447509],"iteration":985,"passed_time":0.947678713,"remaining_time":0.01345588436},
{"learn":[3.113046742],"iteration":986,"passed_time":0.9483352463,"remaining_time":0.01249073779},
{"learn":[3.111157287],"iteration":987,"passed_time":0.9490802364,"remaining_time":0.01152729032},
{"learn":[3.110019516],"iteration":988,"passed_time":0.9497572695,"remaining_time":0.01056352878},
{"learn":[3.109906716],"iteration":989,"passed_time":0.9504573442,"remaining_time":0.009600579235},
{"learn":[3.108355668],"iteration":990,"passed_time":0.9511095856,"remaining_time":0.008637725803},
{"learn":[3.106630608],"iteration":991,"passed_time":0.9519929079,"remaining_time":0.007677362161},
{"learn":[3.104986953],"iteration":992,"passed_time":0.9527596478,"remaining_time":0.006716331857},
{"learn":[3.103829953],"iteration":993,"passed_time":0.9535475964,"remaining_time":0.005755820501},
{"learn":[3.101942068],"iteration":994,"passed_time":0.9541724221,"remaining_time":0.004794836292},
{"learn":[3.101802849],"iteration":995,"passed_time":0.9548166636,"remaining_time":0.003834605075},
{"learn":[3.101603967],"iteration":996,"passed_time":0.9554319474,"remaining_time":0.002874920604},
{"learn":[3.100429521],"iteration":997,"passed_time":0.9560769389,"remaining_time":0.00191598585},
{"learn":[3.099702038],"iteration":998,"passed_time":0.9567045976,"remaining_time":0.0009576622599},
{"learn":[3.098389205],"iteration":999,"passed_time":0.9573470061,"remaining_time":0}
]}